{"updatedAt":"2026-07-01T03:54:07.942Z","wind":{"barbados":{"speed":17.6,"dir":79,"cloud_cover":98,"temperature":25.3,"precipitation":0,"uv_index":0,"hourly":[{"time":"2026-06-30T00:00","speed":20.8,"dir":72,"cloud_cover":89,"uv_index":0,"temperature":25.3,"precip_prob":50},{"time":"2026-06-30T01:00","speed":18.4,"dir":69,"cloud_cover":98,"uv_index":0,"temperature":24.8,"precip_prob":49},{"time":"2026-06-30T02:00","speed":19,"dir":72,"cloud_cover":95,"uv_index":0,"temperature":24.3,"precip_prob":49},{"time":"2026-06-30T03:00","speed":19,"dir":73,"cloud_cover":97,"uv_index":0,"temperature":24.4,"precip_prob":50},{"time":"2026-06-30T04:00","speed":18.7,"dir":72,"cloud_cover":98,"uv_index":0,"temperature":23.8,"precip_prob":53},{"time":"2026-06-30T05:00","speed":18.5,"dir":69,"cloud_cover":96,"uv_index":0,"temperature":24.1,"precip_prob":51},{"time":"2026-06-30T06:00","speed":20,"dir":71,"cloud_cover":53,"uv_index":0.05,"temperature":24.6,"precip_prob":42},{"time":"2026-06-30T07:00","speed":22.2,"dir":75,"cloud_cover":12,"uv_index":0.7,"temperature":25.8,"precip_prob":29},{"time":"2026-06-30T08:00","speed":24.6,"dir":75,"cloud_cover":5,"uv_index":2.3,"temperature":27.6,"precip_prob":18},{"time":"2026-06-30T09:00","speed":23.9,"dir":78,"cloud_cover":6,"uv_index":3.8,"temperature":28.5,"precip_prob":11},{"time":"2026-06-30T10:00","speed":23,"dir":81,"cloud_cover":33,"uv_index":5.45,"temperature":29.3,"precip_prob":5},{"time":"2026-06-30T11:00","speed":23.9,"dir":84,"cloud_cover":100,"uv_index":8.05,"temperature":29.5,"precip_prob":2},{"time":"2026-06-30T12:00","speed":24,"dir":83,"cloud_cover":87,"uv_index":8.85,"temperature":28.5,"precip_prob":1},{"time":"2026-06-30T13:00","speed":23.8,"dir":83,"cloud_cover":100,"uv_index":8.9,"temperature":29.3,"precip_prob":3},{"time":"2026-06-30T14:00","speed":23.4,"dir":82,"cloud_cover":100,"uv_index":8.1,"temperature":29.6,"precip_prob":4},{"time":"2026-06-30T15:00","speed":22.6,"dir":84,"cloud_cover":100,"uv_index":6.6,"temperature":29.1,"precip_prob":4},{"time":"2026-06-30T16:00","speed":21.5,"dir":87,"cloud_cover":100,"uv_index":4.65,"temperature":27.7,"precip_prob":3},{"time":"2026-06-30T17:00","speed":20.9,"dir":87,"cloud_cover":99,"uv_index":2.55,"temperature":27.2,"precip_prob":2},{"time":"2026-06-30T18:00","speed":19.5,"dir":84,"cloud_cover":92,"uv_index":0.85,"temperature":26.3,"precip_prob":2},{"time":"2026-06-30T19:00","speed":18.5,"dir":80,"cloud_cover":67,"uv_index":0.05,"temperature":25.7,"precip_prob":1},{"time":"2026-06-30T20:00","speed":18.3,"dir":80,"cloud_cover":98,"uv_index":0,"temperature":25.5,"precip_prob":2},{"time":"2026-06-30T21:00","speed":17.8,"dir":79,"cloud_cover":99,"uv_index":0,"temperature":25.5,"precip_prob":4},{"time":"2026-06-30T22:00","speed":17.9,"dir":80,"cloud_cover":98,"uv_index":0,"temperature":25.6,"precip_prob":7},{"time":"2026-06-30T23:00","speed":17.2,"dir":80,"cloud_cover":100,"uv_index":0,"temperature":25.4,"precip_prob":10},{"time":"2026-07-01T00:00","speed":17.7,"dir":78,"cloud_cover":98,"uv_index":0,"temperature":25.3,"precip_prob":14},{"time":"2026-07-01T01:00","speed":17.3,"dir":75,"cloud_cover":98,"uv_index":0,"temperature":24.7,"precip_prob":19},{"time":"2026-07-01T02:00","speed":18.7,"dir":72,"cloud_cover":88,"uv_index":0,"temperature":24.9,"precip_prob":22},{"time":"2026-07-01T03:00","speed":19.7,"dir":69,"cloud_cover":88,"uv_index":0,"temperature":24.8,"precip_prob":23},{"time":"2026-07-01T04:00","speed":19.9,"dir":70,"cloud_cover":98,"uv_index":0,"temperature":24.9,"precip_prob":22},{"time":"2026-07-01T05:00","speed":20.4,"dir":76,"cloud_cover":97,"uv_index":0,"temperature":24.9,"precip_prob":22},{"time":"2026-07-01T06:00","speed":20,"dir":73,"cloud_cover":87,"uv_index":0,"temperature":24.7,"precip_prob":24},{"time":"2026-07-01T07:00","speed":20.8,"dir":73,"cloud_cover":89,"uv_index":0.7,"temperature":25.5,"precip_prob":26},{"time":"2026-07-01T08:00","speed":21.5,"dir":78,"cloud_cover":100,"uv_index":2.3,"temperature":26.8,"precip_prob":27},{"time":"2026-07-01T09:00","speed":24.2,"dir":82,"cloud_cover":100,"uv_index":4.5,"temperature":27.8,"precip_prob":26},{"time":"2026-07-01T10:00","speed":25.2,"dir":83,"cloud_cover":100,"uv_index":6.45,"temperature":28.1,"precip_prob":24},{"time":"2026-07-01T11:00","speed":25.2,"dir":84,"cloud_cover":99,"uv_index":8,"temperature":28.6,"precip_prob":22},{"time":"2026-07-01T12:00","speed":25.4,"dir":86,"cloud_cover":97,"uv_index":8.8,"temperature":28.9,"precip_prob":23},{"time":"2026-07-01T13:00","speed":25,"dir":88,"cloud_cover":80,"uv_index":8.85,"temperature":28.9,"precip_prob":24},{"time":"2026-07-01T14:00","speed":24.5,"dir":89,"cloud_cover":64,"uv_index":8.1,"temperature":29,"precip_prob":24},{"time":"2026-07-01T15:00","speed":23,"dir":89,"cloud_cover":85,"uv_index":6.6,"temperature":28.5,"precip_prob":22},{"time":"2026-07-01T16:00","speed":22.9,"dir":88,"cloud_cover":99,"uv_index":4.65,"temperature":28.2,"precip_prob":18},{"time":"2026-07-01T17:00","speed":22.3,"dir":91,"cloud_cover":95,"uv_index":2.6,"temperature":27.3,"precip_prob":16},{"time":"2026-07-01T18:00","speed":21.4,"dir":89,"cloud_cover":30,"uv_index":0.85,"temperature":26.4,"precip_prob":14},{"time":"2026-07-01T19:00","speed":18.6,"dir":88,"cloud_cover":34,"uv_index":0.05,"temperature":25.7,"precip_prob":14},{"time":"2026-07-01T20:00","speed":17.5,"dir":93,"cloud_cover":34,"uv_index":0,"temperature":24.8,"precip_prob":16},{"time":"2026-07-01T21:00","speed":16.6,"dir":93,"cloud_cover":46,"uv_index":0,"temperature":24.6,"precip_prob":24},{"time":"2026-07-01T22:00","speed":18.4,"dir":89,"cloud_cover":33,"uv_index":0,"temperature":24.5,"precip_prob":36},{"time":"2026-07-01T23:00","speed":17.8,"dir":88,"cloud_cover":47,"uv_index":0,"temperature":23.7,"precip_prob":45},{"time":"2026-07-02T00:00","speed":14.6,"dir":95,"cloud_cover":39,"uv_index":0,"temperature":23.5,"precip_prob":51},{"time":"2026-07-02T01:00","speed":16.2,"dir":99,"cloud_cover":20,"uv_index":0,"temperature":24.2,"precip_prob":54},{"time":"2026-07-02T02:00","speed":15.4,"dir":85,"cloud_cover":48,"uv_index":0,"temperature":23.1,"precip_prob":55},{"time":"2026-07-02T03:00","speed":15,"dir":87,"cloud_cover":17,"uv_index":0,"temperature":23.4,"precip_prob":52},{"time":"2026-07-02T04:00","speed":16.2,"dir":88,"cloud_cover":16,"uv_index":0,"temperature":24,"precip_prob":46},{"time":"2026-07-02T05:00","speed":16,"dir":83,"cloud_cover":16,"uv_index":0,"temperature":24.2,"precip_prob":39},{"time":"2026-07-02T06:00","speed":17.4,"dir":83,"cloud_cover":63,"uv_index":0.05,"temperature":24.6,"precip_prob":31},{"time":"2026-07-02T07:00","speed":19.9,"dir":84,"cloud_cover":72,"uv_index":0.75,"temperature":25.7,"precip_prob":22},{"time":"2026-07-02T08:00","speed":20.8,"dir":85,"cloud_cover":88,"uv_index":2.45,"temperature":26.9,"precip_prob":16},{"time":"2026-07-02T09:00","speed":20.5,"dir":82,"cloud_cover":82,"uv_index":4.35,"temperature":27.9,"precip_prob":14},{"time":"2026-07-02T10:00","speed":21.1,"dir":81,"cloud_cover":98,"uv_index":6.3,"temperature":28.5,"precip_prob":13},{"time":"2026-07-02T11:00","speed":21.5,"dir":86,"cloud_cover":96,"uv_index":8,"temperature":29.2,"precip_prob":14},{"time":"2026-07-02T12:00","speed":20.7,"dir":87,"cloud_cover":100,"uv_index":8.85,"temperature":29.3,"precip_prob":15},{"time":"2026-07-02T13:00","speed":20.6,"dir":85,"cloud_cover":98,"uv_index":8.9,"temperature":29.3,"precip_prob":16},{"time":"2026-07-02T14:00","speed":20.9,"dir":83,"cloud_cover":100,"uv_index":8.1,"temperature":29.1,"precip_prob":18},{"time":"2026-07-02T15:00","speed":22,"dir":82,"cloud_cover":98,"uv_index":6.65,"temperature":28,"precip_prob":21},{"time":"2026-07-02T16:00","speed":19.9,"dir":76,"cloud_cover":98,"uv_index":4.7,"temperature":27.5,"precip_prob":25},{"time":"2026-07-02T17:00","speed":20.8,"dir":75,"cloud_cover":99,"uv_index":2.6,"temperature":26.8,"precip_prob":31},{"time":"2026-07-02T18:00","speed":19.5,"dir":76,"cloud_cover":98,"uv_index":0.85,"temperature":25.8,"precip_prob":41},{"time":"2026-07-02T19:00","speed":17.2,"dir":77,"cloud_cover":100,"uv_index":0.05,"temperature":24.8,"precip_prob":54},{"time":"2026-07-02T20:00","speed":18.3,"dir":85,"cloud_cover":100,"uv_index":0,"temperature":25,"precip_prob":63},{"time":"2026-07-02T21:00","speed":19.1,"dir":85,"cloud_cover":100,"uv_index":0,"temperature":25.4,"precip_prob":66},{"time":"2026-07-02T22:00","speed":19.8,"dir":89,"cloud_cover":100,"uv_index":0,"temperature":24.5,"precip_prob":67},{"time":"2026-07-02T23:00","speed":19.1,"dir":87,"cloud_cover":98,"uv_index":0,"temperature":25.1,"precip_prob":69},{"time":"2026-07-03T00:00","speed":15.5,"dir":89,"cloud_cover":99,"uv_index":0,"temperature":24,"precip_prob":77},{"time":"2026-07-03T01:00","speed":19.9,"dir":99,"cloud_cover":100,"uv_index":0,"temperature":23.5,"precip_prob":86},{"time":"2026-07-03T02:00","speed":14.8,"dir":90,"cloud_cover":98,"uv_index":0,"temperature":23.1,"precip_prob":92},{"time":"2026-07-03T03:00","speed":16.4,"dir":81,"cloud_cover":97,"uv_index":0,"temperature":24.3,"precip_prob":91},{"time":"2026-07-03T04:00","speed":16.4,"dir":81,"cloud_cover":91,"uv_index":0,"temperature":24.1,"precip_prob":86},{"time":"2026-07-03T05:00","speed":12.8,"dir":79,"cloud_cover":100,"uv_index":0,"temperature":22.9,"precip_prob":84},{"time":"2026-07-03T06:00","speed":18.8,"dir":81,"cloud_cover":100,"uv_index":0.05,"temperature":23.5,"precip_prob":87},{"time":"2026-07-03T07:00","speed":19.3,"dir":78,"cloud_cover":100,"uv_index":0.75,"temperature":24.8,"precip_prob":93},{"time":"2026-07-03T08:00","speed":20.8,"dir":86,"cloud_cover":96,"uv_index":2.35,"temperature":25.6,"precip_prob":96},{"time":"2026-07-03T09:00","speed":21.8,"dir":80,"cloud_cover":100,"uv_index":4.25,"temperature":27,"precip_prob":96},{"time":"2026-07-03T10:00","speed":20.1,"dir":84,"cloud_cover":99,"uv_index":6,"temperature":27.7,"precip_prob":93},{"time":"2026-07-03T11:00","speed":26.5,"dir":100,"cloud_cover":100,"uv_index":7.55,"temperature":26.6,"precip_prob":90},{"time":"2026-07-03T12:00","speed":21.1,"dir":94,"cloud_cover":100,"uv_index":7.8,"temperature":26.2,"precip_prob":85},{"time":"2026-07-03T13:00","speed":16.1,"dir":94,"cloud_cover":100,"uv_index":7.5,"temperature":27.3,"precip_prob":79},{"time":"2026-07-03T14:00","speed":20.4,"dir":95,"cloud_cover":100,"uv_index":6,"temperature":26.6,"precip_prob":73},{"time":"2026-07-03T15:00","speed":19.9,"dir":94,"cloud_cover":100,"uv_index":4,"temperature":26,"precip_prob":69},{"time":"2026-07-03T16:00","speed":17.5,"dir":75,"cloud_cover":100,"uv_index":2.75,"temperature":25.8,"precip_prob":65},{"time":"2026-07-03T17:00","speed":19.9,"dir":76,"cloud_cover":100,"uv_index":1.35,"temperature":25.7,"precip_prob":59},{"time":"2026-07-03T18:00","speed":19.8,"dir":74,"cloud_cover":100,"uv_index":0.55,"temperature":25.8,"precip_prob":50},{"time":"2026-07-03T19:00","speed":19.1,"dir":76,"cloud_cover":100,"uv_index":0.05,"temperature":25.4,"precip_prob":40},{"time":"2026-07-03T20:00","speed":18.9,"dir":81,"cloud_cover":100,"uv_index":0,"temperature":25.5,"precip_prob":31},{"time":"2026-07-03T21:00","speed":17.9,"dir":80,"cloud_cover":100,"uv_index":0,"temperature":25.4,"precip_prob":25},{"time":"2026-07-03T22:00","speed":18.2,"dir":81,"cloud_cover":99,"uv_index":0,"temperature":25.4,"precip_prob":21},{"time":"2026-07-03T23:00","speed":18.6,"dir":82,"cloud_cover":99,"uv_index":0,"temperature":25.4,"precip_prob":18},{"time":"2026-07-04T00:00","speed":18.7,"dir":79,"cloud_cover":99,"uv_index":0,"temperature":25.2,"precip_prob":18},{"time":"2026-07-04T01:00","speed":18.2,"dir":78,"cloud_cover":100,"uv_index":0,"temperature":25.1,"precip_prob":20},{"time":"2026-07-04T02:00","speed":17.3,"dir":77,"cloud_cover":100,"uv_index":0,"temperature":25.1,"precip_prob":22},{"time":"2026-07-04T03:00","speed":17.6,"dir":79,"cloud_cover":98,"uv_index":0,"temperature":25,"precip_prob":23},{"time":"2026-07-04T04:00","speed":17.8,"dir":74,"cloud_cover":92,"uv_index":0,"temperature":24,"precip_prob":25},{"time":"2026-07-04T05:00","speed":19.8,"dir":77,"cloud_cover":82,"uv_index":0,"temperature":24,"precip_prob":27},{"time":"2026-07-04T06:00","speed":19.4,"dir":80,"cloud_cover":67,"uv_index":0,"temperature":24.3,"precip_prob":32},{"time":"2026-07-04T07:00","speed":22.4,"dir":77,"cloud_cover":77,"uv_index":0.65,"temperature":26.1,"precip_prob":38},{"time":"2026-07-04T08:00","speed":24.6,"dir":76,"cloud_cover":66,"uv_index":2,"temperature":26.8,"precip_prob":41},{"time":"2026-07-04T09:00","speed":25.1,"dir":79,"cloud_cover":76,"uv_index":4.15,"temperature":27.2,"precip_prob":37},{"time":"2026-07-04T10:00","speed":25.1,"dir":82,"cloud_cover":91,"uv_index":6.5,"temperature":27.4,"precip_prob":30},{"time":"2026-07-04T11:00","speed":25,"dir":84,"cloud_cover":100,"uv_index":7.1,"temperature":27.5,"precip_prob":24},{"time":"2026-07-04T12:00","speed":24.6,"dir":85,"cloud_cover":98,"uv_index":5.9,"temperature":27.6,"precip_prob":20},{"time":"2026-07-04T13:00","speed":23.9,"dir":85,"cloud_cover":90,"uv_index":6.1,"temperature":27.7,"precip_prob":16},{"time":"2026-07-04T14:00","speed":23.2,"dir":84,"cloud_cover":82,"uv_index":5.55,"temperature":27.6,"precip_prob":14},{"time":"2026-07-04T15:00","speed":22.9,"dir":82,"cloud_cover":75,"uv_index":4.35,"temperature":27.3,"precip_prob":13},{"time":"2026-07-04T16:00","speed":22.7,"dir":79,"cloud_cover":68,"uv_index":3.9,"temperature":26.8,"precip_prob":14},{"time":"2026-07-04T17:00","speed":22.3,"dir":78,"cloud_cover":65,"uv_index":2.05,"temperature":26.3,"precip_prob":18},{"time":"2026-07-04T18:00","speed":21.5,"dir":78,"cloud_cover":71,"uv_index":0.8,"temperature":25.9,"precip_prob":28},{"time":"2026-07-04T19:00","speed":20.3,"dir":79,"cloud_cover":82,"uv_index":0.05,"temperature":25.5,"precip_prob":41},{"time":"2026-07-04T20:00","speed":19.5,"dir":80,"cloud_cover":87,"uv_index":0,"temperature":25.3,"precip_prob":51},{"time":"2026-07-04T21:00","speed":19,"dir":81,"cloud_cover":79,"uv_index":0,"temperature":25.3,"precip_prob":54},{"time":"2026-07-04T22:00","speed":18.6,"dir":81,"cloud_cover":66,"uv_index":0,"temperature":25.5,"precip_prob":55},{"time":"2026-07-04T23:00","speed":18.2,"dir":81,"cloud_cover":59,"uv_index":0,"temperature":25.4,"precip_prob":55},{"time":"2026-07-05T00:00","speed":17.6,"dir":82,"cloud_cover":66,"uv_index":0,"temperature":24.7,"precip_prob":56},{"time":"2026-07-05T01:00","speed":17.3,"dir":82,"cloud_cover":80,"uv_index":0,"temperature":23.8,"precip_prob":57},{"time":"2026-07-05T02:00","speed":16.9,"dir":82,"cloud_cover":84,"uv_index":0,"temperature":23.3,"precip_prob":59},{"time":"2026-07-05T03:00","speed":17,"dir":81,"cloud_cover":68,"uv_index":0,"temperature":23.3,"precip_prob":65},{"time":"2026-07-05T04:00","speed":17.4,"dir":80,"cloud_cover":43,"uv_index":0,"temperature":23.7,"precip_prob":73},{"time":"2026-07-05T05:00","speed":17.8,"dir":79,"cloud_cover":28,"uv_index":0,"temperature":24.2,"precip_prob":78},{"time":"2026-07-05T06:00","speed":18.1,"dir":81,"cloud_cover":35,"uv_index":0.05,"temperature":24.7,"precip_prob":78},{"time":"2026-07-05T07:00","speed":18.3,"dir":83,"cloud_cover":52,"uv_index":0.7,"temperature":25.3,"precip_prob":75},{"time":"2026-07-05T08:00","speed":19,"dir":85,"cloud_cover":65,"uv_index":2.4,"temperature":26,"precip_prob":71},{"time":"2026-07-05T09:00","speed":20.4,"dir":85,"cloud_cover":68,"uv_index":4.5,"temperature":26.8,"precip_prob":68},{"time":"2026-07-05T10:00","speed":22.2,"dir":84,"cloud_cover":66,"uv_index":6.5,"temperature":27.7,"precip_prob":64},{"time":"2026-07-05T11:00","speed":23.5,"dir":84,"cloud_cover":65,"uv_index":8,"temperature":28.4,"precip_prob":59},{"time":"2026-07-05T12:00","speed":23.6,"dir":86,"cloud_cover":67,"uv_index":8.85,"temperature":28.9,"precip_prob":52},{"time":"2026-07-05T13:00","speed":23.4,"dir":87,"cloud_cover":71,"uv_index":8.7,"temperature":29.3,"precip_prob":44},{"time":"2026-07-05T14:00","speed":23.1,"dir":88,"cloud_cover":71,"uv_index":7.6,"temperature":29.3,"precip_prob":39},{"time":"2026-07-05T15:00","speed":23.1,"dir":86,"cloud_cover":64,"uv_index":6.15,"temperature":28.9,"precip_prob":38},{"time":"2026-07-05T16:00","speed":23.2,"dir":83,"cloud_cover":55,"uv_index":4.4,"temperature":28.2,"precip_prob":40},{"time":"2026-07-05T17:00","speed":22.9,"dir":81,"cloud_cover":53,"uv_index":2.65,"temperature":27.5,"precip_prob":43},{"time":"2026-07-05T18:00","speed":21.8,"dir":81,"cloud_cover":68,"uv_index":1.1,"temperature":26.7,"precip_prob":49},{"time":"2026-07-05T19:00","speed":20.2,"dir":82,"cloud_cover":90,"uv_index":0.1,"temperature":26,"precip_prob":56},{"time":"2026-07-05T20:00","speed":19,"dir":83,"cloud_cover":100,"uv_index":0,"temperature":25.4,"precip_prob":63},{"time":"2026-07-05T21:00","speed":18.6,"dir":86,"cloud_cover":85,"uv_index":0,"temperature":25.2,"precip_prob":69},{"time":"2026-07-05T22:00","speed":18.6,"dir":87,"cloud_cover":57,"uv_index":0,"temperature":25.2,"precip_prob":74},{"time":"2026-07-05T23:00","speed":18.4,"dir":89,"cloud_cover":35,"uv_index":0,"temperature":25.1,"precip_prob":78},{"time":"2026-07-06T00:00","speed":17.5,"dir":89,"cloud_cover":23,"uv_index":0,"temperature":24.8,"precip_prob":79},{"time":"2026-07-06T01:00","speed":16.4,"dir":89,"cloud_cover":17,"uv_index":0,"temperature":24.5,"precip_prob":77},{"time":"2026-07-06T02:00","speed":15.7,"dir":88,"cloud_cover":20,"uv_index":0,"temperature":24.1,"precip_prob":76},{"time":"2026-07-06T03:00","speed":15.2,"dir":85,"cloud_cover":40,"uv_index":0,"temperature":23.5,"precip_prob":75},{"time":"2026-07-06T04:00","speed":15.1,"dir":82,"cloud_cover":69,"uv_index":0,"temperature":22.8,"precip_prob":74},{"time":"2026-07-06T05:00","speed":15.7,"dir":80,"cloud_cover":84,"uv_index":0,"temperature":22.8,"precip_prob":73},{"time":"2026-07-06T06:00","speed":17.4,"dir":82,"cloud_cover":69,"uv_index":0.05,"temperature":24,"precip_prob":74},{"time":"2026-07-06T07:00","speed":19.9,"dir":86,"cloud_cover":40,"uv_index":0.95,"temperature":26,"precip_prob":76},{"time":"2026-07-06T08:00","speed":21.8,"dir":88,"cloud_cover":21,"uv_index":2.1,"temperature":27.5,"precip_prob":76},{"time":"2026-07-06T09:00","speed":22.7,"dir":89,"cloud_cover":24,"uv_index":3.7,"temperature":28.3,"precip_prob":73},{"time":"2026-07-06T10:00","speed":22.9,"dir":90,"cloud_cover":37,"uv_index":5.65,"temperature":28.8,"precip_prob":69},{"time":"2026-07-06T11:00","speed":22.7,"dir":90,"cloud_cover":48,"uv_index":7.4,"temperature":29,"precip_prob":65},{"time":"2026-07-06T12:00","speed":21.8,"dir":87,"cloud_cover":51,"uv_index":8.45,"temperature":29.1,"precip_prob":62},{"time":"2026-07-06T13:00","speed":20.6,"dir":84,"cloud_cover":53,"uv_index":8.75,"temperature":28.9,"precip_prob":59},{"time":"2026-07-06T14:00","speed":19.9,"dir":81,"cloud_cover":53,"uv_index":8.2,"temperature":28.8,"precip_prob":59},{"time":"2026-07-06T15:00","speed":21.5,"dir":78,"cloud_cover":47,"uv_index":6.85,"temperature":29.1,"precip_prob":63},{"time":"2026-07-06T16:00","speed":21,"dir":78,"cloud_cover":44,"uv_index":4.95,"temperature":28.3,"precip_prob":69},{"time":"2026-07-06T17:00","speed":20.5,"dir":77,"cloud_cover":40,"uv_index":3,"temperature":27.3,"precip_prob":74},{"time":"2026-07-06T18:00","speed":19.9,"dir":76,"cloud_cover":36,"uv_index":1.25,"temperature":26.2,"precip_prob":75},{"time":"2026-07-06T19:00","speed":19.3,"dir":75,"cloud_cover":33,"uv_index":0.1,"temperature":25.3,"precip_prob":74},{"time":"2026-07-06T20:00","speed":18.8,"dir":75,"cloud_cover":34,"uv_index":0,"temperature":24.6,"precip_prob":73},{"time":"2026-07-06T21:00","speed":18.3,"dir":75,"cloud_cover":39,"uv_index":0,"temperature":24.1,"precip_prob":74},{"time":"2026-07-06T22:00","speed":17.9,"dir":75,"cloud_cover":47,"uv_index":0,"temperature":23.8,"precip_prob":75},{"time":"2026-07-06T23:00","speed":17.2,"dir":76,"cloud_cover":56,"uv_index":0,"temperature":23.5,"precip_prob":77}]}},"bankCount":15,"banks":[{"id":1,"island":"barbados","centroid":[13.487,-58.414],"mass":0.27,"count":4,"hull":[[13.487,-58.469],[13.487,-58.361]],"drift":{"speed":2.5,"bearing":166,"predictions":{"6h":{"centroid":[13.379,-58.359],"hull":[[13.379,-58.414],[13.379,-58.306]],"beached":false,"confidence":75},"12h":{"centroid":[13.252,-58.366],"hull":[[13.252,-58.421],[13.252,-58.313]],"beached":false,"confidence":55},"24h":{"centroid":[13.295,-58.615],"hull":[[13.295,-58.67],[13.295,-58.562]],"beached":false,"confidence":35},"48h":{"centroid":[13.408,-58.659],"hull":[[13.408,-58.714],[13.408,-58.606]],"beached":false,"confidence":22},"72h":{"centroid":[13.152,-58.78],"hull":[[13.152,-58.835],[13.152,-58.727]],"beached":false,"confidence":14}}},"threatens":{}},{"id":2,"island":"barbados","centroid":[13.663,-58.368],"mass":0.2,"count":78,"hull":[[13.488,-58.442],[13.56,-58.514],[13.776,-58.514],[13.812,-58.478],[13.812,-58.19],[13.596,-58.19],[13.524,-58.226],[13.488,-58.334]],"drift":{"speed":2.5,"bearing":166,"predictions":{"6h":{"centroid":[13.555,-58.313],"hull":[[13.38,-58.387],[13.452,-58.459],[13.668,-58.459],[13.704,-58.423],[13.704,-58.135],[13.488,-58.135],[13.416,-58.171],[13.38,-58.279]],"beached":false,"confidence":75},"12h":{"centroid":[13.428,-58.32],"hull":[[13.253,-58.394],[13.325,-58.466],[13.541,-58.466],[13.577,-58.43],[13.577,-58.142],[13.361,-58.142],[13.289,-58.178],[13.253,-58.286]],"beached":false,"confidence":55},"24h":{"centroid":[13.471,-58.569],"hull":[[13.296,-58.643],[13.368,-58.715],[13.584,-58.715],[13.62,-58.679],[13.62,-58.391],[13.404,-58.391],[13.332,-58.427],[13.296,-58.535]],"beached":false,"confidence":35},"48h":{"centroid":[13.584,-58.613],"hull":[[13.409,-58.687],[13.481,-58.759],[13.697,-58.759],[13.733,-58.723],[13.733,-58.435],[13.517,-58.435],[13.445,-58.471],[13.409,-58.579]],"beached":false,"confidence":22},"72h":{"centroid":[13.328,-58.734],"hull":[[13.153,-58.808],[13.225,-58.88],[13.441,-58.88],[13.477,-58.844],[13.477,-58.556],[13.261,-58.556],[13.189,-58.592],[13.153,-58.7]],"beached":false,"confidence":14}}},"threatens":{}},{"id":3,"island":"barbados","centroid":[14.089,-60.225],"mass":0.2,"count":10,"hull":[[14.051,-60.339],[14.123,-60.231],[14.159,-60.159],[14.123,-60.123],[14.051,-60.231]],"drift":{"speed":2.5,"bearing":166,"predictions":{"6h":{"centroid":[13.981,-60.17],"hull":[[13.943,-60.284],[14.015,-60.176],[14.051,-60.104],[14.015,-60.068],[13.943,-60.176]],"beached":false,"confidence":75},"12h":{"centroid":[13.854,-60.177],"hull":[[13.816,-60.291],[13.888,-60.183],[13.924,-60.111],[13.888,-60.075],[13.816,-60.183]],"beached":false,"confidence":55},"24h":{"centroid":[13.897,-60.426],"hull":[[13.859,-60.54],[13.931,-60.432],[13.967,-60.36],[13.931,-60.324],[13.859,-60.432]],"beached":false,"confidence":35},"48h":{"centroid":[14.022,-60.435],"hull":[[13.984,-60.549],[14.056,-60.441],[14.092,-60.369],[14.056,-60.333],[13.984,-60.441]],"beached":true,"confidence":22},"72h":{"centroid":[13.897,-60.435],"hull":[[13.859,-60.549],[13.931,-60.441],[13.967,-60.369],[13.931,-60.333],[13.859,-60.441]],"beached":true,"confidence":14}}},"threatens":{}},{"id":4,"island":"barbados","centroid":[13.659,-58.627],"mass":0.17,"count":51,"hull":[[13.489,-58.787],[13.561,-58.823],[13.705,-58.823],[13.777,-58.751],[13.813,-58.679],[13.813,-58.499],[13.525,-58.499]],"drift":{"speed":2.5,"bearing":166,"predictions":{"6h":{"centroid":[13.551,-58.572],"hull":[[13.381,-58.732],[13.453,-58.768],[13.597,-58.768],[13.669,-58.696],[13.705,-58.624],[13.705,-58.444],[13.417,-58.444]],"beached":false,"confidence":75},"12h":{"centroid":[13.424,-58.579],"hull":[[13.254,-58.739],[13.326,-58.775],[13.47,-58.775],[13.542,-58.703],[13.578,-58.631],[13.578,-58.451],[13.29,-58.451]],"beached":false,"confidence":55},"24h":{"centroid":[13.467,-58.828],"hull":[[13.297,-58.988],[13.369,-59.024],[13.513,-59.024],[13.585,-58.952],[13.621,-58.88],[13.621,-58.7],[13.333,-58.7]],"beached":false,"confidence":35},"48h":{"centroid":[13.58,-58.872],"hull":[[13.41,-59.032],[13.482,-59.068],[13.626,-59.068],[13.698,-58.996],[13.734,-58.924],[13.734,-58.744],[13.446,-58.744]],"beached":false,"confidence":22},"72h":{"centroid":[13.324,-58.993],"hull":[[13.154,-59.153],[13.226,-59.189],[13.37,-59.189],[13.442,-59.117],[13.478,-59.045],[13.478,-58.865],[13.19,-58.865]],"beached":false,"confidence":14}}},"threatens":{}},{"id":5,"island":"barbados","centroid":[14.124,-60.348],"mass":0.17,"count":6,"hull":[[14.044,-60.386],[14.152,-60.386],[14.152,-60.314],[14.116,-60.314]],"drift":{"speed":2.5,"bearing":166,"predictions":{"6h":{"centroid":[14.016,-60.293],"hull":[[13.936,-60.331],[14.044,-60.331],[14.044,-60.259],[14.008,-60.259]],"beached":false,"confidence":75},"12h":{"centroid":[13.889,-60.3],"hull":[[13.809,-60.338],[13.917,-60.338],[13.917,-60.266],[13.881,-60.266]],"beached":false,"confidence":55},"24h":{"centroid":[13.932,-60.549],"hull":[[13.852,-60.587],[13.96,-60.587],[13.96,-60.515],[13.924,-60.515]],"beached":false,"confidence":35},"48h":{"centroid":[14.048,-60.586],"hull":[[13.968,-60.624],[14.076,-60.624],[14.076,-60.552],[14.04,-60.552]],"beached":true,"confidence":22},"72h":{"centroid":[13.907,-60.585],"hull":[[13.827,-60.623],[13.935,-60.623],[13.935,-60.551],[13.899,-60.551]],"beached":true,"confidence":14}}},"threatens":{}},{"id":6,"island":"barbados","centroid":[13.95,-58.599],"mass":0.15,"count":47,"hull":[[13.79,-58.72],[13.898,-58.828],[14.114,-58.612],[14.114,-58.504],[13.79,-58.504]],"drift":{"speed":2.5,"bearing":166,"predictions":{"6h":{"centroid":[13.842,-58.544],"hull":[[13.682,-58.665],[13.79,-58.773],[14.006,-58.557],[14.006,-58.449],[13.682,-58.449]],"beached":false,"confidence":75},"12h":{"centroid":[13.715,-58.551],"hull":[[13.555,-58.672],[13.663,-58.78],[13.879,-58.564],[13.879,-58.456],[13.555,-58.456]],"beached":false,"confidence":55},"24h":{"centroid":[13.758,-58.8],"hull":[[13.598,-58.921],[13.706,-59.029],[13.922,-58.813],[13.922,-58.705],[13.598,-58.705]],"beached":false,"confidence":35},"48h":{"centroid":[13.871,-58.844],"hull":[[13.711,-58.965],[13.819,-59.073],[14.035,-58.857],[14.035,-58.749],[13.711,-58.749]],"beached":false,"confidence":22},"72h":{"centroid":[13.615,-58.966],"hull":[[13.455,-59.087],[13.563,-59.195],[13.779,-58.979],[13.779,-58.871],[13.455,-58.871]],"beached":false,"confidence":14}}},"threatens":{}},{"id":7,"island":"barbados","centroid":[13.8,-60.113],"mass":0.14,"count":187,"hull":[[13.388,-60.433],[13.928,-60.433],[14,-60.325],[14.108,-60.145],[14.108,-60.001],[14.072,-59.929],[14.036,-59.893],[13.964,-59.857],[13.892,-59.857],[13.748,-59.893],[13.64,-59.929],[13.568,-60.001],[13.424,-60.253],[13.388,-60.325]],"drift":{"speed":2.5,"bearing":166,"predictions":{"6h":{"centroid":[13.692,-60.058],"hull":[[13.28,-60.378],[13.82,-60.378],[13.892,-60.27],[14,-60.09],[14,-59.946],[13.964,-59.874],[13.928,-59.838],[13.856,-59.802],[13.784,-59.802],[13.64,-59.838],[13.532,-59.874],[13.46,-59.946],[13.316,-60.198],[13.28,-60.27]],"beached":false,"confidence":75},"12h":{"centroid":[13.565,-60.065],"hull":[[13.153,-60.385],[13.693,-60.385],[13.765,-60.277],[13.873,-60.097],[13.873,-59.953],[13.837,-59.881],[13.801,-59.845],[13.729,-59.809],[13.657,-59.809],[13.513,-59.845],[13.405,-59.881],[13.333,-59.953],[13.189,-60.205],[13.153,-60.277]],"beached":false,"confidence":55},"24h":{"centroid":[13.608,-60.314],"hull":[[13.196,-60.634],[13.736,-60.634],[13.808,-60.526],[13.916,-60.346],[13.916,-60.202],[13.88,-60.13],[13.844,-60.094],[13.772,-60.058],[13.7,-60.058],[13.556,-60.094],[13.448,-60.13],[13.376,-60.202],[13.232,-60.454],[13.196,-60.526]],"beached":false,"confidence":35},"48h":{"centroid":[13.75,-60.269],"hull":[[13.338,-60.589],[13.878,-60.589],[13.95,-60.481],[14.058,-60.301],[14.058,-60.157],[14.022,-60.085],[13.986,-60.049],[13.914,-60.013],[13.842,-60.013],[13.698,-60.049],[13.59,-60.085],[13.518,-60.157],[13.374,-60.409],[13.338,-60.481]],"beached":true,"confidence":22},"72h":{"centroid":[13.658,-60.268],"hull":[[13.246,-60.588],[13.786,-60.588],[13.858,-60.48],[13.966,-60.3],[13.966,-60.156],[13.93,-60.084],[13.894,-60.048],[13.822,-60.012],[13.75,-60.012],[13.606,-60.048],[13.498,-60.084],[13.426,-60.156],[13.282,-60.408],[13.246,-60.48]],"beached":true,"confidence":14}}},"threatens":{}},{"id":8,"island":"barbados","centroid":[13.487,-58.738],"mass":0.14,"count":4,"hull":[[13.487,-58.8],[13.487,-58.692]],"drift":{"speed":2.5,"bearing":166,"predictions":{"6h":{"centroid":[13.379,-58.683],"hull":[[13.379,-58.745],[13.379,-58.637]],"beached":false,"confidence":75},"12h":{"centroid":[13.252,-58.69],"hull":[[13.252,-58.752],[13.252,-58.644]],"beached":false,"confidence":55},"24h":{"centroid":[13.295,-58.939],"hull":[[13.295,-59.001],[13.295,-58.893]],"beached":false,"confidence":35},"48h":{"centroid":[13.408,-58.983],"hull":[[13.408,-59.045],[13.408,-58.937]],"beached":false,"confidence":22},"72h":{"centroid":[13.152,-59.104],"hull":[[13.152,-59.166],[13.152,-59.058]],"beached":false,"confidence":14}}},"threatens":{}},{"id":9,"island":"barbados","centroid":[13.658,-58.932],"mass":0.13,"count":52,"hull":[[13.489,-58.834],[13.525,-58.942],[13.633,-59.122],[13.813,-59.122],[13.813,-58.978],[13.777,-58.87],[13.741,-58.798],[13.525,-58.798]],"drift":{"speed":2.5,"bearing":166,"predictions":{"6h":{"centroid":[13.55,-58.877],"hull":[[13.381,-58.779],[13.417,-58.887],[13.525,-59.067],[13.705,-59.067],[13.705,-58.923],[13.669,-58.815],[13.633,-58.743],[13.417,-58.743]],"beached":false,"confidence":75},"12h":{"centroid":[13.423,-58.884],"hull":[[13.254,-58.786],[13.29,-58.894],[13.398,-59.074],[13.578,-59.074],[13.578,-58.93],[13.542,-58.822],[13.506,-58.75],[13.29,-58.75]],"beached":false,"confidence":55},"24h":{"centroid":[13.466,-59.133],"hull":[[13.297,-59.035],[13.333,-59.143],[13.441,-59.323],[13.621,-59.323],[13.621,-59.179],[13.585,-59.071],[13.549,-58.999],[13.333,-58.999]],"beached":false,"confidence":35},"48h":{"centroid":[13.579,-59.177],"hull":[[13.41,-59.079],[13.446,-59.187],[13.554,-59.367],[13.734,-59.367],[13.734,-59.223],[13.698,-59.115],[13.662,-59.043],[13.446,-59.043]],"beached":false,"confidence":22},"72h":{"centroid":[13.423,-59.189],"hull":[[13.254,-59.091],[13.29,-59.199],[13.398,-59.379],[13.578,-59.379],[13.578,-59.235],[13.542,-59.127],[13.506,-59.055],[13.29,-59.055]],"beached":true,"confidence":14}}},"threatens":{}},{"id":10,"island":"barbados","centroid":[13.932,-58.396],"mass":0.13,"count":32,"hull":[[13.794,-58.509],[14.01,-58.509],[14.118,-58.473],[14.118,-58.437],[13.938,-58.257],[13.83,-58.185],[13.794,-58.185]],"drift":{"speed":2.5,"bearing":166,"predictions":{"6h":{"centroid":[13.824,-58.341],"hull":[[13.686,-58.454],[13.902,-58.454],[14.01,-58.418],[14.01,-58.382],[13.83,-58.202],[13.722,-58.13],[13.686,-58.13]],"beached":false,"confidence":75},"12h":{"centroid":[13.697,-58.348],"hull":[[13.559,-58.461],[13.775,-58.461],[13.883,-58.425],[13.883,-58.389],[13.703,-58.209],[13.595,-58.137],[13.559,-58.137]],"beached":false,"confidence":55},"24h":{"centroid":[13.74,-58.597],"hull":[[13.602,-58.71],[13.818,-58.71],[13.926,-58.674],[13.926,-58.638],[13.746,-58.458],[13.638,-58.386],[13.602,-58.386]],"beached":false,"confidence":35},"48h":{"centroid":[13.853,-58.641],"hull":[[13.715,-58.754],[13.931,-58.754],[14.039,-58.718],[14.039,-58.682],[13.859,-58.502],[13.751,-58.43],[13.715,-58.43]],"beached":false,"confidence":22},"72h":{"centroid":[13.597,-58.763],"hull":[[13.459,-58.876],[13.675,-58.876],[13.783,-58.84],[13.783,-58.804],[13.603,-58.624],[13.495,-58.552],[13.459,-58.552]],"beached":false,"confidence":14}}},"threatens":{}},{"id":11,"island":"barbados","centroid":[14.139,-59.216],"mass":0.12,"count":10,"hull":[[14.113,-59.281],[14.149,-59.317],[14.149,-59.101],[14.113,-59.101]],"drift":{"speed":2.5,"bearing":166,"predictions":{"6h":{"centroid":[14.031,-59.161],"hull":[[14.005,-59.226],[14.041,-59.262],[14.041,-59.046],[14.005,-59.046]],"beached":false,"confidence":75},"12h":{"centroid":[13.904,-59.168],"hull":[[13.878,-59.233],[13.914,-59.269],[13.914,-59.053],[13.878,-59.053]],"beached":false,"confidence":55},"24h":{"centroid":[13.947,-59.417],"hull":[[13.921,-59.482],[13.957,-59.518],[13.957,-59.302],[13.921,-59.302]],"beached":false,"confidence":35},"48h":{"centroid":[14.068,-59.437],"hull":[[14.042,-59.502],[14.078,-59.538],[14.078,-59.322],[14.042,-59.322]],"beached":true,"confidence":22},"72h":{"centroid":[13.938,-59.436],"hull":[[13.912,-59.501],[13.948,-59.537],[13.948,-59.321],[13.912,-59.321]],"beached":true,"confidence":14}}},"threatens":{}},{"id":12,"island":"barbados","centroid":[13.992,-58.946],"mass":0.12,"count":7,"hull":[[13.89,-59.119],[13.998,-59.119],[14.106,-59.047],[14.106,-58.939],[13.89,-58.795]],"drift":{"speed":2.5,"bearing":166,"predictions":{"6h":{"centroid":[13.884,-58.891],"hull":[[13.782,-59.064],[13.89,-59.064],[13.998,-58.992],[13.998,-58.884],[13.782,-58.74]],"beached":false,"confidence":75},"12h":{"centroid":[13.757,-58.898],"hull":[[13.655,-59.071],[13.763,-59.071],[13.871,-58.999],[13.871,-58.891],[13.655,-58.747]],"beached":false,"confidence":55},"24h":{"centroid":[13.8,-59.147],"hull":[[13.698,-59.32],[13.806,-59.32],[13.914,-59.248],[13.914,-59.14],[13.698,-58.996]],"beached":false,"confidence":35},"48h":{"centroid":[13.913,-59.191],"hull":[[13.811,-59.364],[13.919,-59.364],[14.027,-59.292],[14.027,-59.184],[13.811,-59.04]],"beached":false,"confidence":22},"72h":{"centroid":[13.726,-59.237],"hull":[[13.624,-59.41],[13.732,-59.41],[13.84,-59.338],[13.84,-59.23],[13.624,-59.086]],"beached":true,"confidence":14}}},"threatens":{}},{"id":13,"island":"barbados","centroid":[14.083,-58.757],"mass":0.12,"count":5,"hull":[[14.052,-58.725],[14.088,-58.797],[14.088,-58.653]],"drift":{"speed":2.5,"bearing":166,"predictions":{"6h":{"centroid":[13.975,-58.702],"hull":[[13.944,-58.67],[13.98,-58.742],[13.98,-58.598]],"beached":false,"confidence":75},"12h":{"centroid":[13.848,-58.709],"hull":[[13.817,-58.677],[13.853,-58.749],[13.853,-58.605]],"beached":false,"confidence":55},"24h":{"centroid":[13.891,-58.958],"hull":[[13.86,-58.926],[13.896,-58.998],[13.896,-58.854]],"beached":false,"confidence":35},"48h":{"centroid":[14.004,-59.002],"hull":[[13.973,-58.97],[14.009,-59.042],[14.009,-58.898]],"beached":false,"confidence":22},"72h":{"centroid":[13.748,-59.124],"hull":[[13.717,-59.092],[13.753,-59.164],[13.753,-59.02]],"beached":false,"confidence":14}}},"threatens":{}},{"id":14,"island":"barbados","centroid":[14.126,-59.058],"mass":0.11,"count":6,"hull":[[14.115,-59.096],[14.151,-59.096],[14.151,-59.06],[14.115,-58.988]],"drift":{"speed":2.5,"bearing":166,"predictions":{"6h":{"centroid":[14.018,-59.003],"hull":[[14.007,-59.041],[14.043,-59.041],[14.043,-59.005],[14.007,-58.933]],"beached":false,"confidence":75},"12h":{"centroid":[13.891,-59.01],"hull":[[13.88,-59.048],[13.916,-59.048],[13.916,-59.012],[13.88,-58.94]],"beached":false,"confidence":55},"24h":{"centroid":[13.934,-59.259],"hull":[[13.923,-59.297],[13.959,-59.297],[13.959,-59.261],[13.923,-59.189]],"beached":false,"confidence":35},"48h":{"centroid":[14.047,-59.303],"hull":[[14.036,-59.341],[14.072,-59.341],[14.072,-59.305],[14.036,-59.233]],"beached":false,"confidence":22},"72h":{"centroid":[13.889,-59.317],"hull":[[13.878,-59.355],[13.914,-59.355],[13.914,-59.319],[13.878,-59.247]],"beached":true,"confidence":14}}},"threatens":{}},{"id":15,"island":"barbados","centroid":[13.254,-59.517],"mass":0.11,"count":5,"hull":[[13.21,-59.473],[13.246,-59.545],[13.318,-59.545]],"drift":{"speed":2.5,"bearing":166,"predictions":{"6h":{"centroid":[13.225,-59.502],"hull":[[13.199,-59.473],[13.226,-59.527],[13.289,-59.53]],"beached":true,"confidence":75},"12h":{"centroid":[13.223,-59.511],"hull":[[13.198,-59.479],[13.232,-59.529],[13.287,-59.539]],"beached":true,"confidence":55},"24h":{"centroid":[13.241,-59.53],"hull":[[13.197,-59.486],[13.242,-59.54],[13.305,-59.558]],"beached":true,"confidence":35},"48h":{"centroid":[13.251,-59.525],"hull":[[13.207,-59.481],[13.246,-59.544],[13.315,-59.553]],"beached":true,"confidence":22},"72h":{"centroid":[13.247,-59.525],"hull":[[13.203,-59.481],[13.243,-59.544],[13.311,-59.553]],"beached":true,"confidence":14}}},"threatens":{"now":[{"id":"bb008","km":4},{"id":"bb002","km":14},{"id":"bb003","km":16},{"id":"bb009","km":17},{"id":"bb007","km":19},{"id":"bb010","km":20},{"id":"bb004","km":21},{"id":"bb006","km":21},{"id":"bb011","km":21},{"id":"bb001","km":22},{"id":"bb005","km":22},{"id":"bb012","km":22}],"6h":[{"id":"bb008","km":2},{"id":"bb009","km":13},{"id":"bb002","km":15},{"id":"bb007","km":15},{"id":"bb003","km":16},{"id":"bb006","km":18},{"id":"bb004","km":19},{"id":"bb005","km":19},{"id":"bb010","km":19},{"id":"bb011","km":19},{"id":"bb012","km":19},{"id":"bb001","km":20}],"12h":[{"id":"bb008","km":1},{"id":"bb002","km":14},{"id":"bb009","km":14},{"id":"bb003","km":15},{"id":"bb007","km":15},{"id":"bb004","km":18},{"id":"bb006","km":18},{"id":"bb010","km":18},{"id":"bb012","km":18},{"id":"bb005","km":19},{"id":"bb011","km":19},{"id":"bb001","km":20}],"24h":[{"id":"bb008","km":3},{"id":"bb002","km":12},{"id":"bb003","km":14},{"id":"bb009","km":17},{"id":"bb007","km":18},{"id":"bb010","km":18},{"id":"bb011","km":19},{"id":"bb001","km":20},{"id":"bb004","km":20},{"id":"bb005","km":20},{"id":"bb006","km":20},{"id":"bb012","km":20}]}}]}