{"updatedAt":"2026-06-05T16:32:24.899Z","wind":{"mq":{"speed":17,"dir":83,"cloud_cover":75,"temperature":27.6,"precipitation":0.3,"uv_index":8.9,"hourly":[{"time":"2026-06-05T00:00","speed":15.5,"dir":63,"cloud_cover":76,"uv_index":0,"temperature":25.1,"precip_prob":0},{"time":"2026-06-05T01:00","speed":14.5,"dir":65,"cloud_cover":77,"uv_index":0,"temperature":25.1,"precip_prob":0},{"time":"2026-06-05T02:00","speed":13,"dir":56,"cloud_cover":58,"uv_index":0,"temperature":24.6,"precip_prob":0},{"time":"2026-06-05T03:00","speed":12.5,"dir":54,"cloud_cover":55,"uv_index":0,"temperature":24.5,"precip_prob":0},{"time":"2026-06-05T04:00","speed":12.8,"dir":59,"cloud_cover":53,"uv_index":0,"temperature":24.6,"precip_prob":0},{"time":"2026-06-05T05:00","speed":12,"dir":64,"cloud_cover":34,"uv_index":0,"temperature":24.4,"precip_prob":4},{"time":"2026-06-05T06:00","speed":11.4,"dir":62,"cloud_cover":43,"uv_index":0.05,"temperature":24.4,"precip_prob":18},{"time":"2026-06-05T07:00","speed":13.3,"dir":57,"cloud_cover":34,"uv_index":0.7,"temperature":25.5,"precip_prob":38},{"time":"2026-06-05T08:00","speed":14.5,"dir":70,"cloud_cover":78,"uv_index":2.25,"temperature":26.6,"precip_prob":57},{"time":"2026-06-05T09:00","speed":15.7,"dir":74,"cloud_cover":68,"uv_index":4,"temperature":27.6,"precip_prob":73},{"time":"2026-06-05T10:00","speed":16.6,"dir":77,"cloud_cover":74,"uv_index":6.3,"temperature":28.8,"precip_prob":88},{"time":"2026-06-05T11:00","speed":16.8,"dir":81,"cloud_cover":45,"uv_index":7.95,"temperature":28.7,"precip_prob":98},{"time":"2026-06-05T12:00","speed":17.8,"dir":84,"cloud_cover":60,"uv_index":8.8,"temperature":27.2,"precip_prob":100},{"time":"2026-06-05T13:00","speed":16.2,"dir":82,"cloud_cover":88,"uv_index":8.85,"temperature":28,"precip_prob":100},{"time":"2026-06-05T14:00","speed":16.8,"dir":78,"cloud_cover":91,"uv_index":8.15,"temperature":27.4,"precip_prob":100},{"time":"2026-06-05T15:00","speed":16.2,"dir":77,"cloud_cover":100,"uv_index":6.7,"temperature":28.1,"precip_prob":100},{"time":"2026-06-05T16:00","speed":15.5,"dir":72,"cloud_cover":27,"uv_index":4.7,"temperature":28.2,"precip_prob":98},{"time":"2026-06-05T17:00","speed":14.8,"dir":67,"cloud_cover":41,"uv_index":2.65,"temperature":27.4,"precip_prob":90},{"time":"2026-06-05T18:00","speed":14.3,"dir":65,"cloud_cover":39,"uv_index":0.9,"temperature":26.3,"precip_prob":67},{"time":"2026-06-05T19:00","speed":13.1,"dir":69,"cloud_cover":39,"uv_index":0.05,"temperature":24.8,"precip_prob":38},{"time":"2026-06-05T20:00","speed":13.4,"dir":64,"cloud_cover":20,"uv_index":0,"temperature":24.8,"precip_prob":18},{"time":"2026-06-05T21:00","speed":13.6,"dir":67,"cloud_cover":13,"uv_index":0,"temperature":24.8,"precip_prob":17},{"time":"2026-06-05T22:00","speed":13,"dir":68,"cloud_cover":31,"uv_index":0,"temperature":24.9,"precip_prob":25},{"time":"2026-06-05T23:00","speed":12.6,"dir":65,"cloud_cover":45,"uv_index":0,"temperature":24.5,"precip_prob":33},{"time":"2026-06-06T00:00","speed":12.9,"dir":65,"cloud_cover":39,"uv_index":0,"temperature":24.7,"precip_prob":38},{"time":"2026-06-06T01:00","speed":13.2,"dir":56,"cloud_cover":85,"uv_index":0,"temperature":23.8,"precip_prob":43},{"time":"2026-06-06T02:00","speed":11.4,"dir":57,"cloud_cover":52,"uv_index":0,"temperature":23.7,"precip_prob":45},{"time":"2026-06-06T03:00","speed":12.8,"dir":112,"cloud_cover":100,"uv_index":0,"temperature":21.8,"precip_prob":44},{"time":"2026-06-06T04:00","speed":12,"dir":54,"cloud_cover":25,"uv_index":0,"temperature":22.3,"precip_prob":42},{"time":"2026-06-06T05:00","speed":12.9,"dir":51,"cloud_cover":21,"uv_index":0,"temperature":22.7,"precip_prob":37},{"time":"2026-06-06T06:00","speed":12.2,"dir":59,"cloud_cover":59,"uv_index":0.05,"temperature":23.4,"precip_prob":29},{"time":"2026-06-06T07:00","speed":15.1,"dir":81,"cloud_cover":87,"uv_index":0.65,"temperature":24.9,"precip_prob":20},{"time":"2026-06-06T08:00","speed":18.4,"dir":82,"cloud_cover":77,"uv_index":2.35,"temperature":27.1,"precip_prob":14},{"time":"2026-06-06T09:00","speed":20.6,"dir":80,"cloud_cover":100,"uv_index":4.45,"temperature":28.5,"precip_prob":13},{"time":"2026-06-06T10:00","speed":20.7,"dir":90,"cloud_cover":98,"uv_index":5.7,"temperature":28.4,"precip_prob":16},{"time":"2026-06-06T11:00","speed":19.6,"dir":82,"cloud_cover":95,"uv_index":6.3,"temperature":29.4,"precip_prob":20},{"time":"2026-06-06T12:00","speed":20.7,"dir":83,"cloud_cover":15,"uv_index":7.75,"temperature":29.9,"precip_prob":25},{"time":"2026-06-06T13:00","speed":20.9,"dir":89,"cloud_cover":73,"uv_index":7.5,"temperature":29.8,"precip_prob":31},{"time":"2026-06-06T14:00","speed":19.5,"dir":86,"cloud_cover":69,"uv_index":6.6,"temperature":29.5,"precip_prob":37},{"time":"2026-06-06T15:00","speed":18.6,"dir":78,"cloud_cover":93,"uv_index":4.6,"temperature":29,"precip_prob":42},{"time":"2026-06-06T16:00","speed":18.4,"dir":76,"cloud_cover":77,"uv_index":3.65,"temperature":27.9,"precip_prob":46},{"time":"2026-06-06T17:00","speed":18.5,"dir":79,"cloud_cover":40,"uv_index":2.3,"temperature":27.5,"precip_prob":47},{"time":"2026-06-06T18:00","speed":16.5,"dir":80,"cloud_cover":39,"uv_index":0.75,"temperature":26.8,"precip_prob":42},{"time":"2026-06-06T19:00","speed":14,"dir":74,"cloud_cover":42,"uv_index":0.05,"temperature":26.2,"precip_prob":33},{"time":"2026-06-06T20:00","speed":15.7,"dir":77,"cloud_cover":47,"uv_index":0,"temperature":25.9,"precip_prob":25},{"time":"2026-06-06T21:00","speed":15.1,"dir":75,"cloud_cover":99,"uv_index":0,"temperature":25.5,"precip_prob":18},{"time":"2026-06-06T22:00","speed":15.4,"dir":73,"cloud_cover":95,"uv_index":0,"temperature":25.6,"precip_prob":11},{"time":"2026-06-06T23:00","speed":15.7,"dir":74,"cloud_cover":100,"uv_index":0,"temperature":25.5,"precip_prob":6},{"time":"2026-06-07T00:00","speed":15.8,"dir":69,"cloud_cover":92,"uv_index":0,"temperature":25.3,"precip_prob":5},{"time":"2026-06-07T01:00","speed":14.9,"dir":71,"cloud_cover":35,"uv_index":0,"temperature":25.3,"precip_prob":7},{"time":"2026-06-07T02:00","speed":13.1,"dir":71,"cloud_cover":30,"uv_index":0,"temperature":25,"precip_prob":8},{"time":"2026-06-07T03:00","speed":12.9,"dir":83,"cloud_cover":66,"uv_index":0,"temperature":25,"precip_prob":7},{"time":"2026-06-07T04:00","speed":13.8,"dir":70,"cloud_cover":63,"uv_index":0,"temperature":24.8,"precip_prob":5},{"time":"2026-06-07T05:00","speed":13.2,"dir":61,"cloud_cover":78,"uv_index":0,"temperature":24.5,"precip_prob":4},{"time":"2026-06-07T06:00","speed":14.1,"dir":65,"cloud_cover":80,"uv_index":0.05,"temperature":24.7,"precip_prob":4},{"time":"2026-06-07T07:00","speed":15.2,"dir":73,"cloud_cover":95,"uv_index":0.7,"temperature":25.3,"precip_prob":5},{"time":"2026-06-07T08:00","speed":18.4,"dir":67,"cloud_cover":88,"uv_index":2.3,"temperature":26.1,"precip_prob":8},{"time":"2026-06-07T09:00","speed":22,"dir":70,"cloud_cover":40,"uv_index":4.05,"temperature":27.9,"precip_prob":14},{"time":"2026-06-07T10:00","speed":22.7,"dir":72,"cloud_cover":48,"uv_index":6,"temperature":28.9,"precip_prob":22},{"time":"2026-06-07T11:00","speed":22.7,"dir":74,"cloud_cover":88,"uv_index":7.1,"temperature":29.6,"precip_prob":29},{"time":"2026-06-07T12:00","speed":22.2,"dir":77,"cloud_cover":95,"uv_index":8,"temperature":30,"precip_prob":36},{"time":"2026-06-07T13:00","speed":22.3,"dir":76,"cloud_cover":91,"uv_index":8.75,"temperature":29.9,"precip_prob":42},{"time":"2026-06-07T14:00","speed":21.9,"dir":74,"cloud_cover":84,"uv_index":8.2,"temperature":30,"precip_prob":45},{"time":"2026-06-07T15:00","speed":22.4,"dir":73,"cloud_cover":98,"uv_index":6.75,"temperature":29.4,"precip_prob":44},{"time":"2026-06-07T16:00","speed":22.3,"dir":76,"cloud_cover":98,"uv_index":4.75,"temperature":28.8,"precip_prob":39},{"time":"2026-06-07T17:00","speed":21.1,"dir":74,"cloud_cover":99,"uv_index":2.65,"temperature":27.6,"precip_prob":33},{"time":"2026-06-07T18:00","speed":18,"dir":72,"cloud_cover":93,"uv_index":0.9,"temperature":26.7,"precip_prob":24},{"time":"2026-06-07T19:00","speed":15.5,"dir":70,"cloud_cover":95,"uv_index":0.05,"temperature":25.8,"precip_prob":14},{"time":"2026-06-07T20:00","speed":15.5,"dir":65,"cloud_cover":99,"uv_index":0,"temperature":25.3,"precip_prob":6},{"time":"2026-06-07T21:00","speed":16.3,"dir":62,"cloud_cover":84,"uv_index":0,"temperature":25.3,"precip_prob":3},{"time":"2026-06-07T22:00","speed":17.4,"dir":60,"cloud_cover":38,"uv_index":0,"temperature":25.5,"precip_prob":3},{"time":"2026-06-07T23:00","speed":16.2,"dir":63,"cloud_cover":41,"uv_index":0,"temperature":25.5,"precip_prob":4},{"time":"2026-06-08T00:00","speed":14.7,"dir":65,"cloud_cover":27,"uv_index":0,"temperature":25.3,"precip_prob":8},{"time":"2026-06-08T01:00","speed":14,"dir":67,"cloud_cover":30,"uv_index":0,"temperature":25.1,"precip_prob":14},{"time":"2026-06-08T02:00","speed":14.8,"dir":67,"cloud_cover":61,"uv_index":0,"temperature":25.1,"precip_prob":18},{"time":"2026-06-08T03:00","speed":15.4,"dir":58,"cloud_cover":65,"uv_index":0,"temperature":24.6,"precip_prob":17},{"time":"2026-06-08T04:00","speed":16.2,"dir":64,"cloud_cover":99,"uv_index":0,"temperature":24.6,"precip_prob":14},{"time":"2026-06-08T05:00","speed":16.2,"dir":63,"cloud_cover":100,"uv_index":0,"temperature":24.4,"precip_prob":12},{"time":"2026-06-08T06:00","speed":16.6,"dir":66,"cloud_cover":98,"uv_index":0.05,"temperature":24.5,"precip_prob":13},{"time":"2026-06-08T07:00","speed":18.3,"dir":68,"cloud_cover":84,"uv_index":0.75,"temperature":25.1,"precip_prob":15},{"time":"2026-06-08T08:00","speed":21,"dir":63,"cloud_cover":63,"uv_index":1.95,"temperature":25.7,"precip_prob":18},{"time":"2026-06-08T09:00","speed":23.8,"dir":61,"cloud_cover":38,"uv_index":3.45,"temperature":27.2,"precip_prob":20},{"time":"2026-06-08T10:00","speed":23.3,"dir":64,"cloud_cover":23,"uv_index":4.2,"temperature":28.5,"precip_prob":23},{"time":"2026-06-08T11:00","speed":23.1,"dir":65,"cloud_cover":26,"uv_index":4.8,"temperature":29,"precip_prob":25},{"time":"2026-06-08T12:00","speed":22.6,"dir":63,"cloud_cover":84,"uv_index":5.55,"temperature":29,"precip_prob":28},{"time":"2026-06-08T13:00","speed":22.1,"dir":64,"cloud_cover":85,"uv_index":7.05,"temperature":29.1,"precip_prob":30},{"time":"2026-06-08T14:00","speed":21.9,"dir":66,"cloud_cover":73,"uv_index":5.65,"temperature":28.9,"precip_prob":31},{"time":"2026-06-08T15:00","speed":22.1,"dir":64,"cloud_cover":96,"uv_index":4.7,"temperature":28.1,"precip_prob":30},{"time":"2026-06-08T16:00","speed":20.8,"dir":64,"cloud_cover":98,"uv_index":4.25,"temperature":27.3,"precip_prob":29},{"time":"2026-06-08T17:00","speed":19.5,"dir":64,"cloud_cover":98,"uv_index":2.6,"temperature":26.3,"precip_prob":25},{"time":"2026-06-08T18:00","speed":17.6,"dir":64,"cloud_cover":38,"uv_index":0.9,"temperature":25.6,"precip_prob":18},{"time":"2026-06-08T19:00","speed":15.3,"dir":62,"cloud_cover":45,"uv_index":0.05,"temperature":24.9,"precip_prob":10},{"time":"2026-06-08T20:00","speed":16.3,"dir":62,"cloud_cover":46,"uv_index":0,"temperature":25,"precip_prob":4},{"time":"2026-06-08T21:00","speed":16.3,"dir":64,"cloud_cover":44,"uv_index":0,"temperature":25,"precip_prob":1},{"time":"2026-06-08T22:00","speed":16.5,"dir":67,"cloud_cover":50,"uv_index":0,"temperature":25.1,"precip_prob":0},{"time":"2026-06-08T23:00","speed":16.5,"dir":68,"cloud_cover":58,"uv_index":0,"temperature":25.1,"precip_prob":0},{"time":"2026-06-09T00:00","speed":15.9,"dir":67,"cloud_cover":71,"uv_index":0,"temperature":25.1,"precip_prob":1},{"time":"2026-06-09T01:00","speed":15,"dir":63,"cloud_cover":87,"uv_index":0,"temperature":25,"precip_prob":3},{"time":"2026-06-09T02:00","speed":14.3,"dir":61,"cloud_cover":97,"uv_index":0,"temperature":24.9,"precip_prob":4},{"time":"2026-06-09T03:00","speed":13.5,"dir":60,"cloud_cover":97,"uv_index":0,"temperature":24.7,"precip_prob":4},{"time":"2026-06-09T04:00","speed":12.8,"dir":61,"cloud_cover":91,"uv_index":0,"temperature":24.6,"precip_prob":4},{"time":"2026-06-09T05:00","speed":12.8,"dir":62,"cloud_cover":83,"uv_index":0,"temperature":24.6,"precip_prob":4},{"time":"2026-06-09T06:00","speed":14.2,"dir":64,"cloud_cover":70,"uv_index":0.05,"temperature":24.9,"precip_prob":6},{"time":"2026-06-09T07:00","speed":16.4,"dir":67,"cloud_cover":55,"uv_index":0.7,"temperature":25.4,"precip_prob":8},{"time":"2026-06-09T08:00","speed":18.2,"dir":69,"cloud_cover":48,"uv_index":2.35,"temperature":26,"precip_prob":12},{"time":"2026-06-09T09:00","speed":19.1,"dir":69,"cloud_cover":58,"uv_index":4.45,"temperature":27.1,"precip_prob":18},{"time":"2026-06-09T10:00","speed":19.7,"dir":69,"cloud_cover":76,"uv_index":5.6,"temperature":28.4,"precip_prob":26},{"time":"2026-06-09T11:00","speed":19.7,"dir":69,"cloud_cover":91,"uv_index":6.8,"temperature":29.3,"precip_prob":31},{"time":"2026-06-09T12:00","speed":19.1,"dir":66,"cloud_cover":98,"uv_index":8.6,"temperature":29.3,"precip_prob":32},{"time":"2026-06-09T13:00","speed":18.2,"dir":63,"cloud_cover":100,"uv_index":7.6,"temperature":28.9,"precip_prob":31},{"time":"2026-06-09T14:00","speed":17.4,"dir":60,"cloud_cover":100,"uv_index":6.85,"temperature":28.4,"precip_prob":29},{"time":"2026-06-09T15:00","speed":17.3,"dir":59,"cloud_cover":96,"uv_index":5.1,"temperature":27.8,"precip_prob":26},{"time":"2026-06-09T16:00","speed":17.5,"dir":60,"cloud_cover":89,"uv_index":4.2,"temperature":27.1,"precip_prob":21},{"time":"2026-06-09T17:00","speed":17.1,"dir":60,"cloud_cover":80,"uv_index":2.65,"temperature":26.4,"precip_prob":16},{"time":"2026-06-09T18:00","speed":15.4,"dir":58,"cloud_cover":68,"uv_index":0.9,"temperature":25.8,"precip_prob":11},{"time":"2026-06-09T19:00","speed":13.2,"dir":56,"cloud_cover":53,"uv_index":0.05,"temperature":25.2,"precip_prob":6},{"time":"2026-06-09T20:00","speed":11.6,"dir":54,"cloud_cover":43,"uv_index":0,"temperature":24.8,"precip_prob":2},{"time":"2026-06-09T21:00","speed":11.1,"dir":53,"cloud_cover":40,"uv_index":0,"temperature":24.6,"precip_prob":1},{"time":"2026-06-09T22:00","speed":11.2,"dir":52,"cloud_cover":41,"uv_index":0,"temperature":24.7,"precip_prob":1},{"time":"2026-06-09T23:00","speed":11.2,"dir":52,"cloud_cover":43,"uv_index":0,"temperature":24.7,"precip_prob":2},{"time":"2026-06-10T00:00","speed":11.2,"dir":52,"cloud_cover":47,"uv_index":0,"temperature":24.5,"precip_prob":3},{"time":"2026-06-10T01:00","speed":11.3,"dir":53,"cloud_cover":52,"uv_index":0,"temperature":24.3,"precip_prob":4},{"time":"2026-06-10T02:00","speed":11.3,"dir":53,"cloud_cover":56,"uv_index":0,"temperature":24.2,"precip_prob":4},{"time":"2026-06-10T03:00","speed":11.2,"dir":52,"cloud_cover":60,"uv_index":0,"temperature":24,"precip_prob":3},{"time":"2026-06-10T04:00","speed":11.3,"dir":51,"cloud_cover":63,"uv_index":0,"temperature":23.8,"precip_prob":3},{"time":"2026-06-10T05:00","speed":11.6,"dir":53,"cloud_cover":64,"uv_index":0,"temperature":24,"precip_prob":2},{"time":"2026-06-10T06:00","speed":12.8,"dir":56,"cloud_cover":60,"uv_index":0.1,"temperature":24.8,"precip_prob":1},{"time":"2026-06-10T07:00","speed":14.5,"dir":60,"cloud_cover":55,"uv_index":0.35,"temperature":26,"precip_prob":1},{"time":"2026-06-10T08:00","speed":16.1,"dir":63,"cloud_cover":55,"uv_index":1.05,"temperature":27.1,"precip_prob":4},{"time":"2026-06-10T09:00","speed":17.1,"dir":66,"cloud_cover":68,"uv_index":2.6,"temperature":28.2,"precip_prob":14},{"time":"2026-06-10T10:00","speed":17.8,"dir":69,"cloud_cover":87,"uv_index":4.65,"temperature":29.2,"precip_prob":27},{"time":"2026-06-10T11:00","speed":18.1,"dir":70,"cloud_cover":96,"uv_index":6.3,"temperature":29.9,"precip_prob":37},{"time":"2026-06-10T12:00","speed":17.8,"dir":67,"cloud_cover":83,"uv_index":7.35,"temperature":30.2,"precip_prob":39},{"time":"2026-06-10T13:00","speed":16.9,"dir":63,"cloud_cover":60,"uv_index":8.05,"temperature":30.1,"precip_prob":38},{"time":"2026-06-10T14:00","speed":16.4,"dir":60,"cloud_cover":45,"uv_index":8.1,"temperature":29.8,"precip_prob":37},{"time":"2026-06-10T15:00","speed":16.2,"dir":60,"cloud_cover":50,"uv_index":7.25,"temperature":29.3,"precip_prob":40},{"time":"2026-06-10T16:00","speed":16.1,"dir":61,"cloud_cover":64,"uv_index":5.85,"temperature":28.6,"precip_prob":43},{"time":"2026-06-10T17:00","speed":16,"dir":60,"cloud_cover":71,"uv_index":4.35,"temperature":27.9,"precip_prob":43},{"time":"2026-06-10T18:00","speed":15.4,"dir":57,"cloud_cover":61,"uv_index":2.9,"temperature":27.1,"precip_prob":35},{"time":"2026-06-10T19:00","speed":14.5,"dir":54,"cloud_cover":44,"uv_index":1.4,"temperature":26.3,"precip_prob":23},{"time":"2026-06-10T20:00","speed":14,"dir":52,"cloud_cover":33,"uv_index":0.3,"temperature":25.7,"precip_prob":14},{"time":"2026-06-10T21:00","speed":13.6,"dir":54,"cloud_cover":36,"uv_index":0,"temperature":25.4,"precip_prob":10},{"time":"2026-06-10T22:00","speed":13.4,"dir":58,"cloud_cover":46,"uv_index":0,"temperature":25.3,"precip_prob":8},{"time":"2026-06-10T23:00","speed":13.4,"dir":61,"cloud_cover":53,"uv_index":0,"temperature":25.3,"precip_prob":6},{"time":"2026-06-11T00:00","speed":13,"dir":64,"cloud_cover":53,"uv_index":0,"temperature":25.2,"precip_prob":4},{"time":"2026-06-11T01:00","speed":12.6,"dir":66,"cloud_cover":50,"uv_index":0,"temperature":25.1,"precip_prob":3},{"time":"2026-06-11T02:00","speed":12.4,"dir":68,"cloud_cover":48,"uv_index":0,"temperature":25.1,"precip_prob":2},{"time":"2026-06-11T03:00","speed":13.3,"dir":65,"cloud_cover":91,"uv_index":0,"temperature":25.5,"precip_prob":2},{"time":"2026-06-11T04:00","speed":14.1,"dir":67,"cloud_cover":80,"uv_index":0,"temperature":25.9,"precip_prob":2},{"time":"2026-06-11T05:00","speed":15.3,"dir":69,"cloud_cover":67,"uv_index":0,"temperature":26.4,"precip_prob":3},{"time":"2026-06-11T06:00","speed":16.3,"dir":70,"cloud_cover":53,"uv_index":0.1,"temperature":26.9,"precip_prob":4},{"time":"2026-06-11T07:00","speed":17.1,"dir":71,"cloud_cover":43,"uv_index":0.35,"temperature":27.4,"precip_prob":7},{"time":"2026-06-11T08:00","speed":17.8,"dir":72,"cloud_cover":39,"uv_index":1,"temperature":27.9,"precip_prob":10},{"time":"2026-06-11T09:00","speed":18.1,"dir":73,"cloud_cover":44,"uv_index":2.5,"temperature":28.4,"precip_prob":15},{"time":"2026-06-11T10:00","speed":18,"dir":74,"cloud_cover":55,"uv_index":4.5,"temperature":29,"precip_prob":22},{"time":"2026-06-11T11:00","speed":17.8,"dir":76,"cloud_cover":69,"uv_index":6.1,"temperature":29.7,"precip_prob":28},{"time":"2026-06-11T12:00","speed":17.6,"dir":77,"cloud_cover":84,"uv_index":7.2,"temperature":30.2,"precip_prob":34},{"time":"2026-06-11T13:00","speed":17.2,"dir":77,"cloud_cover":94,"uv_index":7.95,"temperature":30.5,"precip_prob":39},{"time":"2026-06-11T14:00","speed":16.8,"dir":77,"cloud_cover":98,"uv_index":8.05,"temperature":30.6,"precip_prob":41},{"time":"2026-06-11T15:00","speed":16.4,"dir":75,"cloud_cover":93,"uv_index":7.1,"temperature":30.2,"precip_prob":39},{"time":"2026-06-11T16:00","speed":15.7,"dir":73,"cloud_cover":82,"uv_index":5.45,"temperature":29.4,"precip_prob":35},{"time":"2026-06-11T17:00","speed":14.9,"dir":69,"cloud_cover":67,"uv_index":3.85,"temperature":28.5,"precip_prob":30},{"time":"2026-06-11T18:00","speed":14.2,"dir":64,"cloud_cover":51,"uv_index":2.5,"temperature":27.5,"precip_prob":25},{"time":"2026-06-11T19:00","speed":13.8,"dir":61,"cloud_cover":38,"uv_index":1.2,"temperature":26.6,"precip_prob":19},{"time":"2026-06-11T20:00","speed":13.4,"dir":59,"cloud_cover":29,"uv_index":0.25,"temperature":25.9,"precip_prob":14},{"time":"2026-06-11T21:00","speed":13.2,"dir":60,"cloud_cover":26,"uv_index":0,"temperature":25.5,"precip_prob":11},{"time":"2026-06-11T22:00","speed":13,"dir":61,"cloud_cover":27,"uv_index":0,"temperature":25.1,"precip_prob":8},{"time":"2026-06-11T23:00","speed":12.9,"dir":63,"cloud_cover":29,"uv_index":0,"temperature":24.9,"precip_prob":6}]},"gp":{"speed":18,"dir":119,"cloud_cover":43,"temperature":30.6,"precipitation":0.1,"uv_index":8.95,"hourly":[{"time":"2026-06-05T00:00","speed":13.5,"dir":98,"cloud_cover":16,"uv_index":0,"temperature":26.5,"precip_prob":5},{"time":"2026-06-05T01:00","speed":12,"dir":97,"cloud_cover":20,"uv_index":0,"temperature":26.3,"precip_prob":13},{"time":"2026-06-05T02:00","speed":7.5,"dir":130,"cloud_cover":34,"uv_index":0,"temperature":25.4,"precip_prob":22},{"time":"2026-06-05T03:00","speed":6.2,"dir":111,"cloud_cover":45,"uv_index":0,"temperature":25.1,"precip_prob":35},{"time":"2026-06-05T04:00","speed":4,"dir":120,"cloud_cover":23,"uv_index":0,"temperature":24.9,"precip_prob":50},{"time":"2026-06-05T05:00","speed":5.3,"dir":168,"cloud_cover":50,"uv_index":0,"temperature":24.4,"precip_prob":57},{"time":"2026-06-05T06:00","speed":6.2,"dir":159,"cloud_cover":27,"uv_index":0.05,"temperature":24.8,"precip_prob":48},{"time":"2026-06-05T07:00","speed":10,"dir":120,"cloud_cover":14,"uv_index":0.8,"temperature":26,"precip_prob":32},{"time":"2026-06-05T08:00","speed":14.1,"dir":103,"cloud_cover":21,"uv_index":2.35,"temperature":27.6,"precip_prob":25},{"time":"2026-06-05T09:00","speed":16.7,"dir":109,"cloud_cover":23,"uv_index":4.5,"temperature":28.6,"precip_prob":37},{"time":"2026-06-05T10:00","speed":17.8,"dir":113,"cloud_cover":38,"uv_index":6.45,"temperature":28.9,"precip_prob":59},{"time":"2026-06-05T11:00","speed":17,"dir":117,"cloud_cover":20,"uv_index":8,"temperature":29.8,"precip_prob":76},{"time":"2026-06-05T12:00","speed":17.4,"dir":118,"cloud_cover":27,"uv_index":8.85,"temperature":30.6,"precip_prob":83},{"time":"2026-06-05T13:00","speed":18.4,"dir":121,"cloud_cover":61,"uv_index":8.9,"temperature":30.4,"precip_prob":84},{"time":"2026-06-05T14:00","speed":18.1,"dir":123,"cloud_cover":83,"uv_index":8.15,"temperature":29.8,"precip_prob":86},{"time":"2026-06-05T15:00","speed":17.5,"dir":122,"cloud_cover":52,"uv_index":6.75,"temperature":29.1,"precip_prob":91},{"time":"2026-06-05T16:00","speed":16.2,"dir":119,"cloud_cover":38,"uv_index":4.85,"temperature":28.6,"precip_prob":95},{"time":"2026-06-05T17:00","speed":15.3,"dir":117,"cloud_cover":46,"uv_index":2.7,"temperature":28.6,"precip_prob":92},{"time":"2026-06-05T18:00","speed":12.4,"dir":121,"cloud_cover":34,"uv_index":1,"temperature":27.6,"precip_prob":77},{"time":"2026-06-05T19:00","speed":12,"dir":118,"cloud_cover":19,"uv_index":0.1,"temperature":26.7,"precip_prob":55},{"time":"2026-06-05T20:00","speed":10.4,"dir":113,"cloud_cover":11,"uv_index":0,"temperature":26.5,"precip_prob":37},{"time":"2026-06-05T21:00","speed":10.6,"dir":111,"cloud_cover":10,"uv_index":0,"temperature":26.3,"precip_prob":26},{"time":"2026-06-05T22:00","speed":10,"dir":110,"cloud_cover":9,"uv_index":0,"temperature":26.1,"precip_prob":20},{"time":"2026-06-05T23:00","speed":11,"dir":113,"cloud_cover":23,"uv_index":0,"temperature":26,"precip_prob":20},{"time":"2026-06-06T00:00","speed":10.2,"dir":121,"cloud_cover":55,"uv_index":0,"temperature":26,"precip_prob":32},{"time":"2026-06-06T01:00","speed":11.7,"dir":128,"cloud_cover":26,"uv_index":0,"temperature":25.7,"precip_prob":52},{"time":"2026-06-06T02:00","speed":9.4,"dir":126,"cloud_cover":25,"uv_index":0,"temperature":25.5,"precip_prob":63},{"time":"2026-06-06T03:00","speed":11.6,"dir":136,"cloud_cover":35,"uv_index":0,"temperature":25.3,"precip_prob":59},{"time":"2026-06-06T04:00","speed":10.3,"dir":130,"cloud_cover":33,"uv_index":0,"temperature":25.1,"precip_prob":48},{"time":"2026-06-06T05:00","speed":14.7,"dir":116,"cloud_cover":70,"uv_index":0,"temperature":24.8,"precip_prob":37},{"time":"2026-06-06T06:00","speed":11.7,"dir":115,"cloud_cover":58,"uv_index":0.05,"temperature":24.3,"precip_prob":29},{"time":"2026-06-06T07:00","speed":12.5,"dir":111,"cloud_cover":71,"uv_index":0.8,"temperature":25.5,"precip_prob":22},{"time":"2026-06-06T08:00","speed":14.9,"dir":110,"cloud_cover":62,"uv_index":2.4,"temperature":27.4,"precip_prob":20},{"time":"2026-06-06T09:00","speed":19.4,"dir":119,"cloud_cover":97,"uv_index":4.4,"temperature":28.7,"precip_prob":27},{"time":"2026-06-06T10:00","speed":21.9,"dir":121,"cloud_cover":93,"uv_index":6.05,"temperature":28.7,"precip_prob":39},{"time":"2026-06-06T11:00","speed":23.1,"dir":126,"cloud_cover":88,"uv_index":7.25,"temperature":29.7,"precip_prob":49},{"time":"2026-06-06T12:00","speed":20.9,"dir":125,"cloud_cover":99,"uv_index":7.45,"temperature":30.3,"precip_prob":56},{"time":"2026-06-06T13:00","speed":19.6,"dir":124,"cloud_cover":99,"uv_index":6.1,"temperature":30.4,"precip_prob":60},{"time":"2026-06-06T14:00","speed":19.4,"dir":126,"cloud_cover":100,"uv_index":6.4,"temperature":29.6,"precip_prob":63},{"time":"2026-06-06T15:00","speed":18.2,"dir":123,"cloud_cover":99,"uv_index":5.7,"temperature":28.5,"precip_prob":64},{"time":"2026-06-06T16:00","speed":17,"dir":123,"cloud_cover":100,"uv_index":4.3,"temperature":27.3,"precip_prob":62},{"time":"2026-06-06T17:00","speed":14.1,"dir":120,"cloud_cover":99,"uv_index":2.35,"temperature":26.9,"precip_prob":57},{"time":"2026-06-06T18:00","speed":11,"dir":109,"cloud_cover":99,"uv_index":0.65,"temperature":26.7,"precip_prob":47},{"time":"2026-06-06T19:00","speed":14.1,"dir":109,"cloud_cover":95,"uv_index":0.05,"temperature":25.6,"precip_prob":33},{"time":"2026-06-06T20:00","speed":12.9,"dir":113,"cloud_cover":35,"uv_index":0,"temperature":25.3,"precip_prob":22},{"time":"2026-06-06T21:00","speed":10.8,"dir":116,"cloud_cover":22,"uv_index":0,"temperature":25.4,"precip_prob":15},{"time":"2026-06-06T22:00","speed":13.3,"dir":106,"cloud_cover":30,"uv_index":0,"temperature":26,"precip_prob":9},{"time":"2026-06-06T23:00","speed":14.7,"dir":98,"cloud_cover":16,"uv_index":0,"temperature":26.2,"precip_prob":6},{"time":"2026-06-07T00:00","speed":14.6,"dir":100,"cloud_cover":8,"uv_index":0,"temperature":26.1,"precip_prob":6},{"time":"2026-06-07T01:00","speed":14.2,"dir":99,"cloud_cover":46,"uv_index":0,"temperature":26,"precip_prob":8},{"time":"2026-06-07T02:00","speed":13.8,"dir":107,"cloud_cover":31,"uv_index":0,"temperature":25.9,"precip_prob":10},{"time":"2026-06-07T03:00","speed":12.4,"dir":118,"cloud_cover":42,"uv_index":0,"temperature":25.8,"precip_prob":10},{"time":"2026-06-07T04:00","speed":11.5,"dir":122,"cloud_cover":30,"uv_index":0,"temperature":25.8,"precip_prob":8},{"time":"2026-06-07T05:00","speed":10.9,"dir":114,"cloud_cover":66,"uv_index":0,"temperature":25.5,"precip_prob":8},{"time":"2026-06-07T06:00","speed":11.5,"dir":117,"cloud_cover":96,"uv_index":0.05,"temperature":25.7,"precip_prob":8},{"time":"2026-06-07T07:00","speed":14.1,"dir":112,"cloud_cover":98,"uv_index":0.7,"temperature":27.3,"precip_prob":9},{"time":"2026-06-07T08:00","speed":16.7,"dir":115,"cloud_cover":99,"uv_index":1.45,"temperature":28.4,"precip_prob":12},{"time":"2026-06-07T09:00","speed":19.6,"dir":117,"cloud_cover":100,"uv_index":2.55,"temperature":29.4,"precip_prob":20},{"time":"2026-06-07T10:00","speed":20.9,"dir":114,"cloud_cover":100,"uv_index":3.75,"temperature":29.4,"precip_prob":32},{"time":"2026-06-07T11:00","speed":20.9,"dir":114,"cloud_cover":99,"uv_index":6,"temperature":28.1,"precip_prob":41},{"time":"2026-06-07T12:00","speed":19.9,"dir":113,"cloud_cover":100,"uv_index":8.9,"temperature":29.4,"precip_prob":47},{"time":"2026-06-07T13:00","speed":20.4,"dir":111,"cloud_cover":88,"uv_index":8.6,"temperature":29.6,"precip_prob":52},{"time":"2026-06-07T14:00","speed":20.1,"dir":110,"cloud_cover":86,"uv_index":8,"temperature":28.9,"precip_prob":53},{"time":"2026-06-07T15:00","speed":19.7,"dir":114,"cloud_cover":73,"uv_index":6.8,"temperature":28.9,"precip_prob":50},{"time":"2026-06-07T16:00","speed":19.4,"dir":107,"cloud_cover":90,"uv_index":4.9,"temperature":28.4,"precip_prob":43},{"time":"2026-06-07T17:00","speed":16.6,"dir":100,"cloud_cover":16,"uv_index":2.8,"temperature":28,"precip_prob":35},{"time":"2026-06-07T18:00","speed":15,"dir":96,"cloud_cover":55,"uv_index":1,"temperature":27.5,"precip_prob":25},{"time":"2026-06-07T19:00","speed":13,"dir":92,"cloud_cover":91,"uv_index":0.1,"temperature":26.7,"precip_prob":13},{"time":"2026-06-07T20:00","speed":13.4,"dir":95,"cloud_cover":70,"uv_index":0,"temperature":26.5,"precip_prob":4},{"time":"2026-06-07T21:00","speed":13.4,"dir":97,"cloud_cover":87,"uv_index":0,"temperature":26.4,"precip_prob":1},{"time":"2026-06-07T22:00","speed":14.1,"dir":94,"cloud_cover":92,"uv_index":0,"temperature":26.2,"precip_prob":1},{"time":"2026-06-07T23:00","speed":13.1,"dir":92,"cloud_cover":77,"uv_index":0,"temperature":26.1,"precip_prob":2},{"time":"2026-06-08T00:00","speed":12.3,"dir":94,"cloud_cover":25,"uv_index":0,"temperature":25.9,"precip_prob":3},{"time":"2026-06-08T01:00","speed":12.1,"dir":101,"cloud_cover":38,"uv_index":0,"temperature":25.8,"precip_prob":5},{"time":"2026-06-08T02:00","speed":12,"dir":107,"cloud_cover":79,"uv_index":0,"temperature":25.8,"precip_prob":6},{"time":"2026-06-08T03:00","speed":12.3,"dir":95,"cloud_cover":53,"uv_index":0,"temperature":25.9,"precip_prob":6},{"time":"2026-06-08T04:00","speed":13.9,"dir":94,"cloud_cover":38,"uv_index":0,"temperature":26,"precip_prob":5},{"time":"2026-06-08T05:00","speed":12.9,"dir":99,"cloud_cover":74,"uv_index":0,"temperature":25.7,"precip_prob":4},{"time":"2026-06-08T06:00","speed":13.6,"dir":96,"cloud_cover":96,"uv_index":0.05,"temperature":26,"precip_prob":2},{"time":"2026-06-08T07:00","speed":14.6,"dir":94,"cloud_cover":73,"uv_index":0.25,"temperature":27.1,"precip_prob":0},{"time":"2026-06-08T08:00","speed":17.1,"dir":90,"cloud_cover":43,"uv_index":0.8,"temperature":28.3,"precip_prob":0},{"time":"2026-06-08T09:00","speed":19.3,"dir":91,"cloud_cover":52,"uv_index":4.5,"temperature":29.1,"precip_prob":2},{"time":"2026-06-08T10:00","speed":19.3,"dir":94,"cloud_cover":65,"uv_index":5.8,"temperature":29.6,"precip_prob":6},{"time":"2026-06-08T11:00","speed":19.3,"dir":93,"cloud_cover":99,"uv_index":7.55,"temperature":30.3,"precip_prob":10},{"time":"2026-06-08T12:00","speed":19.5,"dir":93,"cloud_cover":97,"uv_index":6.4,"temperature":30,"precip_prob":15},{"time":"2026-06-08T13:00","speed":20.3,"dir":98,"cloud_cover":78,"uv_index":8.7,"temperature":30,"precip_prob":19},{"time":"2026-06-08T14:00","speed":19.8,"dir":98,"cloud_cover":27,"uv_index":7.15,"temperature":30,"precip_prob":22},{"time":"2026-06-08T15:00","speed":18.7,"dir":97,"cloud_cover":25,"uv_index":4.45,"temperature":29.8,"precip_prob":21},{"time":"2026-06-08T16:00","speed":18.6,"dir":96,"cloud_cover":46,"uv_index":3.85,"temperature":29.3,"precip_prob":18},{"time":"2026-06-08T17:00","speed":18.1,"dir":95,"cloud_cover":70,"uv_index":2.75,"temperature":28.5,"precip_prob":14},{"time":"2026-06-08T18:00","speed":15.9,"dir":96,"cloud_cover":66,"uv_index":1,"temperature":27.5,"precip_prob":9},{"time":"2026-06-08T19:00","speed":13.7,"dir":100,"cloud_cover":63,"uv_index":0.1,"temperature":26.6,"precip_prob":4},{"time":"2026-06-08T20:00","speed":12.4,"dir":98,"cloud_cover":67,"uv_index":0,"temperature":26.5,"precip_prob":0},{"time":"2026-06-08T21:00","speed":11.8,"dir":98,"cloud_cover":77,"uv_index":0,"temperature":26.3,"precip_prob":0},{"time":"2026-06-08T22:00","speed":11.7,"dir":95,"cloud_cover":90,"uv_index":0,"temperature":26.4,"precip_prob":0},{"time":"2026-06-08T23:00","speed":11.7,"dir":94,"cloud_cover":99,"uv_index":0,"temperature":26.4,"precip_prob":0},{"time":"2026-06-09T00:00","speed":11.2,"dir":92,"cloud_cover":99,"uv_index":0,"temperature":26.1,"precip_prob":0},{"time":"2026-06-09T01:00","speed":10.4,"dir":90,"cloud_cover":95,"uv_index":0,"temperature":25.8,"precip_prob":0},{"time":"2026-06-09T02:00","speed":9.9,"dir":90,"cloud_cover":91,"uv_index":0,"temperature":25.6,"precip_prob":0},{"time":"2026-06-09T03:00","speed":9.4,"dir":92,"cloud_cover":89,"uv_index":0,"temperature":25.3,"precip_prob":1},{"time":"2026-06-09T04:00","speed":8.9,"dir":97,"cloud_cover":86,"uv_index":0,"temperature":25.1,"precip_prob":1},{"time":"2026-06-09T05:00","speed":9.4,"dir":101,"cloud_cover":80,"uv_index":0,"temperature":25.2,"precip_prob":2},{"time":"2026-06-09T06:00","speed":11.1,"dir":102,"cloud_cover":65,"uv_index":0.05,"temperature":25.9,"precip_prob":2},{"time":"2026-06-09T07:00","speed":13.6,"dir":102,"cloud_cover":47,"uv_index":0.75,"temperature":26.9,"precip_prob":2},{"time":"2026-06-09T08:00","speed":15.5,"dir":103,"cloud_cover":38,"uv_index":2.4,"temperature":27.8,"precip_prob":4},{"time":"2026-06-09T09:00","speed":16.5,"dir":106,"cloud_cover":48,"uv_index":3.75,"temperature":28.3,"precip_prob":11},{"time":"2026-06-09T10:00","speed":17.1,"dir":110,"cloud_cover":68,"uv_index":3.35,"temperature":28.7,"precip_prob":20},{"time":"2026-06-09T11:00","speed":17.3,"dir":113,"cloud_cover":84,"uv_index":4.25,"temperature":29.1,"precip_prob":25},{"time":"2026-06-09T12:00","speed":16.8,"dir":115,"cloud_cover":90,"uv_index":5.55,"temperature":29.7,"precip_prob":23},{"time":"2026-06-09T13:00","speed":15.9,"dir":115,"cloud_cover":93,"uv_index":5.5,"temperature":30.2,"precip_prob":17},{"time":"2026-06-09T14:00","speed":15.1,"dir":115,"cloud_cover":95,"uv_index":7.3,"temperature":30.5,"precip_prob":12},{"time":"2026-06-09T15:00","speed":14.8,"dir":113,"cloud_cover":100,"uv_index":6.75,"temperature":30.2,"precip_prob":9},{"time":"2026-06-09T16:00","speed":14.5,"dir":109,"cloud_cover":100,"uv_index":4.85,"temperature":29.7,"precip_prob":8},{"time":"2026-06-09T17:00","speed":13.6,"dir":105,"cloud_cover":100,"uv_index":2.75,"temperature":29,"precip_prob":6},{"time":"2026-06-09T18:00","speed":11.4,"dir":103,"cloud_cover":73,"uv_index":0.55,"temperature":28.1,"precip_prob":4},{"time":"2026-06-09T19:00","speed":8.8,"dir":101,"cloud_cover":36,"uv_index":0.1,"temperature":27,"precip_prob":2},{"time":"2026-06-09T20:00","speed":6.5,"dir":98,"cloud_cover":11,"uv_index":0,"temperature":26.1,"precip_prob":0},{"time":"2026-06-09T21:00","speed":5.4,"dir":94,"cloud_cover":10,"uv_index":0,"temperature":25.6,"precip_prob":0},{"time":"2026-06-09T22:00","speed":4.7,"dir":92,"cloud_cover":21,"uv_index":0,"temperature":25.4,"precip_prob":0},{"time":"2026-06-09T23:00","speed":4.2,"dir":95,"cloud_cover":27,"uv_index":0,"temperature":25.1,"precip_prob":0},{"time":"2026-06-10T00:00","speed":4,"dir":108,"cloud_cover":20,"uv_index":0,"temperature":24.9,"precip_prob":0},{"time":"2026-06-10T01:00","speed":4.3,"dir":123,"cloud_cover":8,"uv_index":0,"temperature":24.6,"precip_prob":0},{"time":"2026-06-10T02:00","speed":4.6,"dir":132,"cloud_cover":4,"uv_index":0,"temperature":24.5,"precip_prob":0},{"time":"2026-06-10T03:00","speed":3.7,"dir":137,"cloud_cover":15,"uv_index":0,"temperature":24.3,"precip_prob":2},{"time":"2026-06-10T04:00","speed":2.2,"dir":138,"cloud_cover":34,"uv_index":0,"temperature":24.2,"precip_prob":4},{"time":"2026-06-10T05:00","speed":1.9,"dir":119,"cloud_cover":48,"uv_index":0,"temperature":24.5,"precip_prob":6},{"time":"2026-06-10T06:00","speed":4.2,"dir":97,"cloud_cover":51,"uv_index":0.15,"temperature":25.5,"precip_prob":5},{"time":"2026-06-10T07:00","speed":7.7,"dir":93,"cloud_cover":50,"uv_index":0.4,"temperature":26.9,"precip_prob":4},{"time":"2026-06-10T08:00","speed":10.7,"dir":95,"cloud_cover":53,"uv_index":1.1,"temperature":28.2,"precip_prob":4},{"time":"2026-06-10T09:00","speed":12,"dir":104,"cloud_cover":67,"uv_index":2.55,"temperature":29.1,"precip_prob":8},{"time":"2026-06-10T10:00","speed":13.2,"dir":114,"cloud_cover":85,"uv_index":4.45,"temperature":29.8,"precip_prob":15},{"time":"2026-06-10T11:00","speed":14.1,"dir":120,"cloud_cover":96,"uv_index":6,"temperature":30.3,"precip_prob":20},{"time":"2026-06-10T12:00","speed":13.9,"dir":119,"cloud_cover":95,"uv_index":6.95,"temperature":30.6,"precip_prob":23},{"time":"2026-06-10T13:00","speed":13,"dir":114,"cloud_cover":87,"uv_index":7.55,"temperature":30.6,"precip_prob":24},{"time":"2026-06-10T14:00","speed":12.5,"dir":110,"cloud_cover":80,"uv_index":7.65,"temperature":30.3,"precip_prob":24},{"time":"2026-06-10T15:00","speed":12.8,"dir":106,"cloud_cover":77,"uv_index":7.05,"temperature":29.6,"precip_prob":24},{"time":"2026-06-10T16:00","speed":13.3,"dir":103,"cloud_cover":73,"uv_index":5.9,"temperature":28.6,"precip_prob":23},{"time":"2026-06-10T17:00","speed":13.2,"dir":101,"cloud_cover":67,"uv_index":4.6,"temperature":27.8,"precip_prob":20},{"time":"2026-06-10T18:00","speed":11.8,"dir":98,"cloud_cover":53,"uv_index":3.1,"temperature":27.3,"precip_prob":15},{"time":"2026-06-10T19:00","speed":9.9,"dir":93,"cloud_cover":36,"uv_index":1.45,"temperature":26.9,"precip_prob":9},{"time":"2026-06-10T20:00","speed":8.3,"dir":91,"cloud_cover":24,"uv_index":0.25,"temperature":26.5,"precip_prob":4},{"time":"2026-06-10T21:00","speed":7.1,"dir":97,"cloud_cover":21,"uv_index":0,"temperature":26.2,"precip_prob":2},{"time":"2026-06-10T22:00","speed":6.5,"dir":109,"cloud_cover":23,"uv_index":0,"temperature":26,"precip_prob":3},{"time":"2026-06-10T23:00","speed":6.8,"dir":119,"cloud_cover":26,"uv_index":0,"temperature":25.8,"precip_prob":3},{"time":"2026-06-11T00:00","speed":8.1,"dir":121,"cloud_cover":30,"uv_index":0,"temperature":25.8,"precip_prob":3},{"time":"2026-06-11T01:00","speed":10,"dir":118,"cloud_cover":36,"uv_index":0,"temperature":26,"precip_prob":4},{"time":"2026-06-11T02:00","speed":11.5,"dir":117,"cloud_cover":40,"uv_index":0,"temperature":26.1,"precip_prob":4},{"time":"2026-06-11T03:00","speed":11.8,"dir":114,"cloud_cover":99,"uv_index":0,"temperature":26.4,"precip_prob":4},{"time":"2026-06-11T04:00","speed":12.2,"dir":112,"cloud_cover":98,"uv_index":0,"temperature":26.7,"precip_prob":3},{"time":"2026-06-11T05:00","speed":12.5,"dir":108,"cloud_cover":96,"uv_index":0,"temperature":27.2,"precip_prob":3},{"time":"2026-06-11T06:00","speed":12.9,"dir":106,"cloud_cover":92,"uv_index":0.1,"temperature":27.7,"precip_prob":3},{"time":"2026-06-11T07:00","speed":13.4,"dir":104,"cloud_cover":89,"uv_index":0.25,"temperature":28.2,"precip_prob":4},{"time":"2026-06-11T08:00","speed":13.8,"dir":104,"cloud_cover":88,"uv_index":0.7,"temperature":28.6,"precip_prob":6},{"time":"2026-06-11T09:00","speed":14.1,"dir":107,"cloud_cover":89,"uv_index":1.5,"temperature":29,"precip_prob":11},{"time":"2026-06-11T10:00","speed":14.9,"dir":111,"cloud_cover":92,"uv_index":2.65,"temperature":29.5,"precip_prob":18},{"time":"2026-06-11T11:00","speed":15.5,"dir":116,"cloud_cover":95,"uv_index":3.9,"temperature":29.9,"precip_prob":25},{"time":"2026-06-11T12:00","speed":16.3,"dir":121,"cloud_cover":98,"uv_index":5.7,"temperature":30.2,"precip_prob":32},{"time":"2026-06-11T13:00","speed":16.7,"dir":124,"cloud_cover":100,"uv_index":7.65,"temperature":30.4,"precip_prob":38},{"time":"2026-06-11T14:00","speed":16.9,"dir":126,"cloud_cover":100,"uv_index":8.65,"temperature":30.4,"precip_prob":41},{"time":"2026-06-11T15:00","speed":16.2,"dir":126,"cloud_cover":98,"uv_index":8,"temperature":30,"precip_prob":40},{"time":"2026-06-11T16:00","speed":15.2,"dir":125,"cloud_cover":94,"uv_index":6.4,"temperature":29.4,"precip_prob":35},{"time":"2026-06-11T17:00","speed":13.8,"dir":123,"cloud_cover":90,"uv_index":4.75,"temperature":28.6,"precip_prob":30},{"time":"2026-06-11T18:00","speed":12.5,"dir":120,"cloud_cover":85,"uv_index":3.15,"temperature":27.7,"precip_prob":25},{"time":"2026-06-11T19:00","speed":11.4,"dir":117,"cloud_cover":80,"uv_index":1.55,"temperature":27,"precip_prob":19},{"time":"2026-06-11T20:00","speed":10.8,"dir":116,"cloud_cover":77,"uv_index":0.35,"temperature":26.5,"precip_prob":14},{"time":"2026-06-11T21:00","speed":10.7,"dir":115,"cloud_cover":75,"uv_index":0,"temperature":26.2,"precip_prob":11},{"time":"2026-06-11T22:00","speed":11,"dir":115,"cloud_cover":73,"uv_index":0,"temperature":26,"precip_prob":8},{"time":"2026-06-11T23:00","speed":11.6,"dir":116,"cloud_cover":72,"uv_index":0,"temperature":25.9,"precip_prob":6}]}},"bankCount":30,"banks":[{"id":1,"island":"mq","centroid":[14.428,-61.106],"mass":0.16,"count":17,"hull":[[14.325,-61.063],[14.397,-61.171],[14.469,-61.171],[14.469,-60.991],[14.433,-60.955]],"drift":{"speed":1.4,"bearing":243,"predictions":{"6h":{"centroid":[14.452,-61.188],"hull":[[14.349,-61.145],[14.421,-61.253],[14.493,-61.253],[14.493,-61.073],[14.457,-61.037]],"beached":false,"confidence":75},"12h":{"centroid":[14.424,-61.243],"hull":[[14.321,-61.2],[14.393,-61.308],[14.465,-61.308],[14.465,-61.128],[14.429,-61.092]],"beached":false,"confidence":55},"24h":{"centroid":[14.374,-61.378],"hull":[[14.271,-61.335],[14.343,-61.443],[14.415,-61.443],[14.415,-61.263],[14.379,-61.227]],"beached":false,"confidence":35}}},"threatens":{"now":[{"id":"grande-anse","km":9},{"id":"diamant","km":10},{"id":"anse-noire","km":11},{"id":"anse-mitan","km":15},{"id":"anse-madame","km":21},{"id":"pt-marin","km":24},{"id":"sainte-anne","km":24},{"id":"les-salines","km":26}],"6h":[{"id":"grande-anse","km":12},{"id":"anse-noire","km":14},{"id":"diamant","km":17},{"id":"anse-mitan","km":18},{"id":"anse-madame","km":21}],"12h":[{"id":"grande-anse","km":19},{"id":"anse-noire","km":20},{"id":"diamant","km":24},{"id":"anse-mitan","km":25},{"id":"anse-madame","km":26}]}},{"id":2,"island":"mq","centroid":[15.373,-60.672],"mass":0.16,"count":4,"hull":[[15.324,-60.646],[15.36,-60.682],[15.396,-60.682],[15.36,-60.646]],"drift":{"speed":1.4,"bearing":243,"predictions":{"6h":{"centroid":[15.397,-60.754],"hull":[[15.348,-60.728],[15.384,-60.764],[15.42,-60.764],[15.384,-60.728]],"beached":false,"confidence":75},"12h":{"centroid":[15.369,-60.81],"hull":[[15.32,-60.784],[15.356,-60.82],[15.392,-60.82],[15.356,-60.784]],"beached":false,"confidence":55},"24h":{"centroid":[15.319,-60.946],"hull":[[15.27,-60.92],[15.306,-60.956],[15.342,-60.956],[15.306,-60.92]],"beached":false,"confidence":35}}},"threatens":{}},{"id":3,"island":"mq","centroid":[14.998,-60.815],"mass":0.15,"count":31,"hull":[[14.859,-60.869],[14.895,-60.977],[14.967,-60.941],[15.111,-60.833],[15.147,-60.797],[15.183,-60.725],[15.075,-60.653],[15.003,-60.689],[14.895,-60.797],[14.859,-60.833]],"drift":{"speed":1.4,"bearing":243,"predictions":{"6h":{"centroid":[15.022,-60.897],"hull":[[14.883,-60.951],[14.919,-61.059],[14.991,-61.023],[15.135,-60.915],[15.171,-60.879],[15.207,-60.807],[15.099,-60.735],[15.027,-60.771],[14.919,-60.879],[14.883,-60.915]],"beached":false,"confidence":75},"12h":{"centroid":[14.994,-60.953],"hull":[[14.855,-61.007],[14.891,-61.115],[14.963,-61.079],[15.107,-60.971],[15.143,-60.935],[15.179,-60.863],[15.071,-60.791],[14.999,-60.827],[14.891,-60.935],[14.855,-60.971]],"beached":false,"confidence":55},"24h":{"centroid":[14.948,-61.07],"hull":[[14.809,-61.124],[14.845,-61.232],[14.917,-61.196],[15.061,-61.088],[15.097,-61.052],[15.133,-60.98],[15.025,-60.908],[14.953,-60.944],[14.845,-61.052],[14.809,-61.088]],"beached":true,"confidence":35}}},"threatens":{"now":[{"id":"tartane","km":30}],"6h":[{"id":"tartane","km":30}],"12h":[{"id":"tartane","km":27}],"24h":[{"id":"tartane","km":27}]}},{"id":4,"island":"mq","centroid":[14.871,-61.028],"mass":0.15,"count":7,"hull":[[14.812,-60.97],[14.884,-61.078],[14.884,-61.006],[14.848,-60.898]],"drift":{"speed":1.4,"bearing":243,"predictions":{"6h":{"centroid":[14.895,-61.11],"hull":[[14.836,-61.052],[14.908,-61.16],[14.908,-61.088],[14.872,-60.98]],"beached":false,"confidence":75},"12h":{"centroid":[14.867,-61.166],"hull":[[14.808,-61.108],[14.88,-61.216],[14.88,-61.144],[14.844,-61.036]],"beached":false,"confidence":55},"24h":{"centroid":[14.817,-61.301],"hull":[[14.758,-61.243],[14.83,-61.351],[14.83,-61.279],[14.794,-61.171]],"beached":false,"confidence":35}}},"threatens":{"now":[{"id":"tartane","km":17},{"id":"anse-madame","km":29}],"6h":[{"id":"tartane","km":25}],"12h":[{"id":"tartane","km":29},{"id":"anse-madame","km":29}]}},{"id":5,"island":"mq","centroid":[14.974,-61.774],"mass":0.14,"count":15,"hull":[[14.9,-61.865],[15.044,-61.829],[15.08,-61.793],[15.08,-61.757],[15.044,-61.721],[14.936,-61.721],[14.9,-61.793]],"drift":{"speed":1.4,"bearing":243,"predictions":{"6h":{"centroid":[14.998,-61.856],"hull":[[14.924,-61.947],[15.068,-61.911],[15.104,-61.875],[15.104,-61.839],[15.068,-61.803],[14.96,-61.803],[14.924,-61.875]],"beached":false,"confidence":75},"12h":{"centroid":[14.97,-61.912],"hull":[[14.896,-62.003],[15.04,-61.967],[15.076,-61.931],[15.076,-61.895],[15.04,-61.859],[14.932,-61.859],[14.896,-61.931]],"beached":false,"confidence":55},"24h":{"centroid":[14.92,-62.047],"hull":[[14.846,-62.138],[14.99,-62.102],[15.026,-62.066],[15.026,-62.03],[14.99,-61.994],[14.882,-61.994],[14.846,-62.066]],"beached":false,"confidence":35}}},"threatens":{}},{"id":6,"island":"mq","centroid":[14.765,-59.54],"mass":0.13,"count":20,"hull":[[14.617,-59.576],[14.689,-59.612],[14.761,-59.612],[14.869,-59.576],[14.869,-59.504],[14.653,-59.504]],"drift":{"speed":1.4,"bearing":243,"predictions":{"6h":{"centroid":[14.789,-59.622],"hull":[[14.641,-59.658],[14.713,-59.694],[14.785,-59.694],[14.893,-59.658],[14.893,-59.586],[14.677,-59.586]],"beached":false,"confidence":75},"12h":{"centroid":[14.761,-59.678],"hull":[[14.613,-59.714],[14.685,-59.75],[14.757,-59.75],[14.865,-59.714],[14.865,-59.642],[14.649,-59.642]],"beached":false,"confidence":55},"24h":{"centroid":[14.711,-59.813],"hull":[[14.563,-59.849],[14.635,-59.885],[14.707,-59.885],[14.815,-59.849],[14.815,-59.777],[14.599,-59.777]],"beached":false,"confidence":35}}},"threatens":{}},{"id":7,"island":"mq","centroid":[13.994,-61.543],"mass":0.13,"count":7,"hull":[[13.944,-61.587],[14.088,-61.587],[13.98,-61.515],[13.944,-61.515]],"drift":{"speed":1.4,"bearing":243,"predictions":{"6h":{"centroid":[14.018,-61.625],"hull":[[13.968,-61.669],[14.112,-61.669],[14.004,-61.597],[13.968,-61.597]],"beached":false,"confidence":75},"12h":{"centroid":[13.99,-61.68],"hull":[[13.94,-61.724],[14.084,-61.724],[13.976,-61.652],[13.94,-61.652]],"beached":false,"confidence":55},"24h":{"centroid":[13.94,-61.815],"hull":[[13.89,-61.859],[14.034,-61.859],[13.926,-61.787],[13.89,-61.787]],"beached":false,"confidence":35}}},"threatens":{}},{"id":8,"island":"mq","centroid":[13.542,-60.603],"mass":0.12,"count":21,"hull":[[13.494,-60.731],[13.602,-60.659],[13.602,-60.515],[13.494,-60.515]],"drift":{"speed":1.4,"bearing":243,"predictions":{"6h":{"centroid":[13.566,-60.685],"hull":[[13.518,-60.813],[13.626,-60.741],[13.626,-60.597],[13.518,-60.597]],"beached":false,"confidence":75},"12h":{"centroid":[13.538,-60.74],"hull":[[13.49,-60.868],[13.598,-60.796],[13.598,-60.652],[13.49,-60.652]],"beached":false,"confidence":55},"24h":{"centroid":[13.488,-60.874],"hull":[[13.44,-61.002],[13.548,-60.93],[13.548,-60.786],[13.44,-60.786]],"beached":false,"confidence":35}}},"threatens":{}},{"id":9,"island":"mq","centroid":[14.948,-61.326],"mass":0.12,"count":7,"hull":[[14.941,-61.379],[14.977,-61.379],[14.977,-61.307],[14.941,-61.235]],"drift":{"speed":1.4,"bearing":243,"predictions":{"6h":{"centroid":[14.972,-61.408],"hull":[[14.965,-61.461],[15.001,-61.461],[15.001,-61.389],[14.965,-61.317]],"beached":false,"confidence":75},"12h":{"centroid":[14.944,-61.464],"hull":[[14.937,-61.517],[14.973,-61.517],[14.973,-61.445],[14.937,-61.373]],"beached":false,"confidence":55},"24h":{"centroid":[14.894,-61.599],"hull":[[14.887,-61.652],[14.923,-61.652],[14.923,-61.58],[14.887,-61.508]],"beached":false,"confidence":35}}},"threatens":{}},{"id":10,"island":"mq","centroid":[15.122,-61.957],"mass":0.12,"count":6,"hull":[[15.086,-61.973],[15.122,-62.009],[15.158,-61.901],[15.122,-61.901]],"drift":{"speed":1.4,"bearing":243,"predictions":{"6h":{"centroid":[15.146,-62.039],"hull":[[15.11,-62.055],[15.146,-62.091],[15.182,-61.983],[15.146,-61.983]],"beached":false,"confidence":75},"12h":{"centroid":[15.118,-62.095],"hull":[[15.082,-62.111],[15.118,-62.147],[15.154,-62.039],[15.118,-62.039]],"beached":false,"confidence":55},"24h":{"centroid":[15.068,-62.23],"hull":[[15.032,-62.246],[15.068,-62.282],[15.104,-62.174],[15.068,-62.174]],"beached":false,"confidence":35}}},"threatens":{}},{"id":11,"island":"mq","centroid":[13.741,-61.167],"mass":0.12,"count":4,"hull":[[13.706,-61.123],[13.742,-61.195],[13.778,-61.195]],"drift":{"speed":1.4,"bearing":243,"predictions":{"6h":{"centroid":[13.765,-61.249],"hull":[[13.73,-61.205],[13.766,-61.277],[13.802,-61.277]],"beached":false,"confidence":75},"12h":{"centroid":[13.737,-61.304],"hull":[[13.702,-61.26],[13.738,-61.332],[13.774,-61.332]],"beached":false,"confidence":55},"24h":{"centroid":[13.687,-61.439],"hull":[[13.652,-61.395],[13.688,-61.467],[13.724,-61.467]],"beached":false,"confidence":35}}},"threatens":{}},{"id":12,"island":"mq","centroid":[14.561,-61.525],"mass":0.11,"count":219,"hull":[[14.01,-61.303],[14.046,-61.375],[14.154,-61.519],[14.514,-61.987],[14.622,-61.987],[14.874,-61.807],[14.91,-61.771],[14.946,-61.555],[14.802,-61.159],[14.658,-61.123],[14.298,-61.159],[14.154,-61.195],[14.046,-61.267]],"drift":{"speed":1.4,"bearing":243,"predictions":{"6h":{"centroid":[14.585,-61.607],"hull":[[14.034,-61.385],[14.07,-61.457],[14.178,-61.601],[14.538,-62.069],[14.646,-62.069],[14.898,-61.889],[14.934,-61.853],[14.97,-61.637],[14.826,-61.241],[14.682,-61.205],[14.322,-61.241],[14.178,-61.277],[14.07,-61.349]],"beached":false,"confidence":75},"12h":{"centroid":[14.557,-61.662],"hull":[[14.006,-61.44],[14.042,-61.512],[14.15,-61.656],[14.51,-62.124],[14.618,-62.124],[14.87,-61.944],[14.906,-61.908],[14.942,-61.692],[14.798,-61.296],[14.654,-61.26],[14.294,-61.296],[14.15,-61.332],[14.042,-61.404]],"beached":false,"confidence":55},"24h":{"centroid":[14.507,-61.798],"hull":[[13.956,-61.576],[13.992,-61.648],[14.1,-61.792],[14.46,-62.26],[14.568,-62.26],[14.82,-62.08],[14.856,-62.044],[14.892,-61.828],[14.748,-61.432],[14.604,-61.396],[14.244,-61.432],[14.1,-61.468],[13.992,-61.54]],"beached":false,"confidence":35}}},"threatens":{}},{"id":13,"island":"mq","centroid":[14.482,-60.753],"mass":0.11,"count":26,"hull":[[14.35,-60.845],[14.386,-60.845],[14.53,-60.809],[14.602,-60.773],[14.638,-60.737],[14.566,-60.629],[14.458,-60.665],[14.35,-60.773]],"drift":{"speed":1.4,"bearing":243,"predictions":{"6h":{"centroid":[14.506,-60.835],"hull":[[14.374,-60.927],[14.41,-60.927],[14.554,-60.891],[14.626,-60.855],[14.662,-60.819],[14.59,-60.711],[14.482,-60.747],[14.374,-60.855]],"beached":false,"confidence":75},"12h":{"centroid":[14.478,-60.89],"hull":[[14.346,-60.982],[14.382,-60.982],[14.526,-60.946],[14.598,-60.91],[14.634,-60.874],[14.562,-60.766],[14.454,-60.802],[14.346,-60.91]],"beached":false,"confidence":55},"24h":{"centroid":[14.451,-60.913],"hull":[[14.319,-61.005],[14.355,-61.005],[14.499,-60.969],[14.571,-60.933],[14.607,-60.897],[14.535,-60.789],[14.427,-60.825],[14.319,-60.933]],"beached":true,"confidence":35}}},"threatens":{"now":[{"id":"vauclin","km":11},{"id":"pt-marin","km":14},{"id":"sainte-anne","km":15},{"id":"les-salines","km":16},{"id":"diamant","km":30}],"6h":[{"id":"vauclin","km":4},{"id":"pt-marin","km":8},{"id":"sainte-anne","km":10},{"id":"les-salines","km":13},{"id":"diamant","km":21},{"id":"anse-mitan","km":24},{"id":"grande-anse","km":27},{"id":"anse-noire","km":27},{"id":"tartane","km":29}],"12h":[{"id":"pt-marin","km":3},{"id":"sainte-anne","km":5},{"id":"les-salines","km":9},{"id":"vauclin","km":10},{"id":"diamant","km":15},{"id":"anse-mitan","km":20},{"id":"grande-anse","km":21},{"id":"anse-noire","km":22},{"id":"anse-madame","km":28}],"24h":[{"id":"pt-marin","km":3},{"id":"sainte-anne","km":4},{"id":"les-salines","km":8},{"id":"diamant","km":13},{"id":"vauclin","km":14},{"id":"grande-anse","km":19},{"id":"anse-mitan","km":19},{"id":"anse-noire","km":21},{"id":"anse-madame","km":28}]}},{"id":14,"island":"mq","centroid":[15.246,-60.577],"mass":0.11,"count":25,"hull":[[15.133,-60.737],[15.313,-60.593],[15.349,-60.557],[15.457,-60.449],[15.349,-60.449],[15.205,-60.485],[15.133,-60.521]],"drift":{"speed":1.4,"bearing":243,"predictions":{"6h":{"centroid":[15.27,-60.659],"hull":[[15.157,-60.819],[15.337,-60.675],[15.373,-60.639],[15.481,-60.531],[15.373,-60.531],[15.229,-60.567],[15.157,-60.603]],"beached":false,"confidence":75},"12h":{"centroid":[15.242,-60.715],"hull":[[15.129,-60.875],[15.309,-60.731],[15.345,-60.695],[15.453,-60.587],[15.345,-60.587],[15.201,-60.623],[15.129,-60.659]],"beached":false,"confidence":55},"24h":{"centroid":[15.192,-60.85],"hull":[[15.079,-61.01],[15.259,-60.866],[15.295,-60.83],[15.403,-60.722],[15.295,-60.722],[15.151,-60.758],[15.079,-60.794]],"beached":false,"confidence":35}}},"threatens":{}},{"id":15,"island":"mq","centroid":[13.797,-61.415],"mass":0.11,"count":14,"hull":[[13.695,-61.361],[13.731,-61.433],[13.803,-61.505],[13.911,-61.469],[13.839,-61.361]],"drift":{"speed":1.4,"bearing":243,"predictions":{"6h":{"centroid":[13.821,-61.497],"hull":[[13.719,-61.443],[13.755,-61.515],[13.827,-61.587],[13.935,-61.551],[13.863,-61.443]],"beached":false,"confidence":75},"12h":{"centroid":[13.793,-61.552],"hull":[[13.691,-61.498],[13.727,-61.57],[13.799,-61.642],[13.907,-61.606],[13.835,-61.498]],"beached":false,"confidence":55},"24h":{"centroid":[13.743,-61.687],"hull":[[13.641,-61.633],[13.677,-61.705],[13.749,-61.777],[13.857,-61.741],[13.785,-61.633]],"beached":false,"confidence":35}}},"threatens":{}},{"id":16,"island":"gp","centroid":[16.007,-62.071],"mass":0.15,"count":4,"hull":[[16.007,-62.112],[16.007,-62.004]],"drift":{"speed":1.4,"bearing":359,"predictions":{"6h":{"centroid":[16.065,-62.044],"hull":[[16.065,-62.085],[16.065,-61.977]],"beached":false,"confidence":75},"12h":{"centroid":[16.107,-62.002],"hull":[[16.107,-62.043],[16.107,-61.935]],"beached":false,"confidence":55},"24h":{"centroid":[16.289,-61.996],"hull":[[16.289,-62.037],[16.289,-61.929]],"beached":false,"confidence":35}}},"threatens":{"6h":[{"id":"gp-grande-anse","km":30}],"12h":[{"id":"gp-grande-anse","km":25},{"id":"gp-malendure","km":25}],"24h":[{"id":"gp-deshaies","km":22},{"id":"gp-malendure","km":27},{"id":"gp-grande-anse","km":30}]}},{"id":17,"island":"gp","centroid":[16.884,-61.508],"mass":0.14,"count":14,"hull":[[16.804,-61.54],[17.02,-61.576],[17.02,-61.54],[16.984,-61.468],[16.84,-61.468],[16.804,-61.504]],"drift":{"speed":1.4,"bearing":359,"predictions":{"6h":{"centroid":[16.942,-61.481],"hull":[[16.862,-61.513],[17.078,-61.549],[17.078,-61.513],[17.042,-61.441],[16.898,-61.441],[16.862,-61.477]],"beached":false,"confidence":75},"12h":{"centroid":[16.984,-61.439],"hull":[[16.904,-61.471],[17.12,-61.507],[17.12,-61.471],[17.084,-61.399],[16.94,-61.399],[16.904,-61.435]],"beached":false,"confidence":55},"24h":{"centroid":[17.166,-61.433],"hull":[[17.086,-61.465],[17.302,-61.501],[17.302,-61.465],[17.266,-61.393],[17.122,-61.393],[17.086,-61.429]],"beached":false,"confidence":35}}},"threatens":{}},{"id":18,"island":"gp","centroid":[16.645,-61.543],"mass":0.13,"count":9,"hull":[[16.563,-61.533],[16.599,-61.569],[16.707,-61.569],[16.707,-61.497],[16.671,-61.497]],"drift":{"speed":1.4,"bearing":359,"predictions":{"6h":{"centroid":[16.703,-61.516],"hull":[[16.621,-61.506],[16.657,-61.542],[16.765,-61.542],[16.765,-61.47],[16.729,-61.47]],"beached":false,"confidence":75},"12h":{"centroid":[16.745,-61.474],"hull":[[16.663,-61.464],[16.699,-61.5],[16.807,-61.5],[16.807,-61.428],[16.771,-61.428]],"beached":false,"confidence":55},"24h":{"centroid":[16.927,-61.468],"hull":[[16.845,-61.458],[16.881,-61.494],[16.989,-61.494],[16.989,-61.422],[16.953,-61.422]],"beached":false,"confidence":35}}},"threatens":{"now":[{"id":"gp-moule","km":25}]}},{"id":19,"island":"gp","centroid":[15.859,-61.459],"mass":0.13,"count":7,"hull":[[15.785,-61.442],[15.857,-61.514],[15.893,-61.478],[15.893,-61.442],[15.857,-61.406]],"drift":{"speed":1.4,"bearing":359,"predictions":{"6h":{"centroid":[15.917,-61.432],"hull":[[15.843,-61.415],[15.915,-61.487],[15.951,-61.451],[15.951,-61.415],[15.915,-61.379]],"beached":false,"confidence":75},"12h":{"centroid":[15.959,-61.39],"hull":[[15.885,-61.373],[15.957,-61.445],[15.993,-61.409],[15.993,-61.373],[15.957,-61.337]],"beached":false,"confidence":55},"24h":{"centroid":[16.127,-61.388],"hull":[[16.053,-61.371],[16.125,-61.443],[16.161,-61.407],[16.161,-61.371],[16.125,-61.335]],"beached":true,"confidence":35}}},"threatens":{"12h":[{"id":"gp-sainte-anne","km":29},{"id":"gp-caravelle","km":29},{"id":"gp-gosier","km":30}],"24h":[{"id":"gp-caravelle","km":10},{"id":"gp-sainte-anne","km":11},{"id":"gp-gosier","km":14},{"id":"gp-bas-du-fort","km":17},{"id":"gp-pt-chateaux","km":22},{"id":"gp-vieux-fort","km":29}]}},{"id":20,"island":"gp","centroid":[16.675,-60.334],"mass":0.13,"count":6,"hull":[[16.665,-60.407],[16.701,-60.335],[16.665,-60.263]],"drift":{"speed":1.4,"bearing":359,"predictions":{"6h":{"centroid":[16.733,-60.307],"hull":[[16.723,-60.38],[16.759,-60.308],[16.723,-60.236]],"beached":false,"confidence":75},"12h":{"centroid":[16.775,-60.265],"hull":[[16.765,-60.338],[16.801,-60.266],[16.765,-60.194]],"beached":false,"confidence":55},"24h":{"centroid":[16.957,-60.259],"hull":[[16.947,-60.332],[16.983,-60.26],[16.947,-60.188]],"beached":false,"confidence":35}}},"threatens":{}},{"id":21,"island":"gp","centroid":[16.796,-61.116],"mass":0.12,"count":26,"hull":[[16.677,-61.115],[16.713,-61.259],[16.749,-61.295],[16.929,-61.151],[16.929,-61.007],[16.857,-60.935],[16.785,-60.935]],"drift":{"speed":1.4,"bearing":359,"predictions":{"6h":{"centroid":[16.854,-61.089],"hull":[[16.735,-61.088],[16.771,-61.232],[16.807,-61.268],[16.987,-61.124],[16.987,-60.98],[16.915,-60.908],[16.843,-60.908]],"beached":false,"confidence":75},"12h":{"centroid":[16.896,-61.047],"hull":[[16.777,-61.046],[16.813,-61.19],[16.849,-61.226],[17.029,-61.082],[17.029,-60.938],[16.957,-60.866],[16.885,-60.866]],"beached":false,"confidence":55},"24h":{"centroid":[17.078,-61.041],"hull":[[16.959,-61.04],[16.995,-61.184],[17.031,-61.22],[17.211,-61.076],[17.211,-60.932],[17.139,-60.86],[17.067,-60.86]],"beached":false,"confidence":35}}},"threatens":{}},{"id":22,"island":"gp","centroid":[16.422,-61.362],"mass":0.12,"count":9,"hull":[[16.356,-61.318],[16.392,-61.39],[16.5,-61.39],[16.428,-61.318],[16.356,-61.282]],"drift":{"speed":1.4,"bearing":359,"predictions":{"6h":{"centroid":[16.48,-61.335],"hull":[[16.414,-61.291],[16.45,-61.363],[16.558,-61.363],[16.486,-61.291],[16.414,-61.255]],"beached":false,"confidence":75},"12h":{"centroid":[16.522,-61.293],"hull":[[16.456,-61.249],[16.492,-61.321],[16.6,-61.321],[16.528,-61.249],[16.456,-61.213]],"beached":false,"confidence":55},"24h":{"centroid":[16.704,-61.287],"hull":[[16.638,-61.243],[16.674,-61.315],[16.782,-61.315],[16.71,-61.243],[16.638,-61.207]],"beached":false,"confidence":35}}},"threatens":{"now":[{"id":"gp-moule","km":18},{"id":"gp-sainte-anne","km":22},{"id":"gp-pt-chateaux","km":23},{"id":"gp-caravelle","km":23},{"id":"gp-gosier","km":28},{"id":"gp-bas-du-fort","km":29},{"id":"gp-vieux-fort","km":30}],"6h":[{"id":"gp-moule","km":22},{"id":"gp-pt-chateaux","km":28},{"id":"gp-sainte-anne","km":29},{"id":"gp-caravelle","km":30}],"12h":[{"id":"gp-moule","km":28}]}},{"id":23,"island":"gp","centroid":[16.189,-62.321],"mass":0.11,"count":83,"hull":[[15.935,-62.386],[15.971,-62.458],[16.043,-62.53],[16.295,-62.53],[16.511,-62.386],[16.511,-62.242],[16.295,-62.134],[16.187,-62.134],[16.043,-62.17],[15.935,-62.314]],"drift":{"speed":1.4,"bearing":359,"predictions":{"6h":{"centroid":[16.247,-62.294],"hull":[[15.993,-62.359],[16.029,-62.431],[16.101,-62.503],[16.353,-62.503],[16.569,-62.359],[16.569,-62.215],[16.353,-62.107],[16.245,-62.107],[16.101,-62.143],[15.993,-62.287]],"beached":false,"confidence":75},"12h":{"centroid":[16.289,-62.252],"hull":[[16.035,-62.317],[16.071,-62.389],[16.143,-62.461],[16.395,-62.461],[16.611,-62.317],[16.611,-62.173],[16.395,-62.065],[16.287,-62.065],[16.143,-62.101],[16.035,-62.245]],"beached":false,"confidence":55},"24h":{"centroid":[16.471,-62.246],"hull":[[16.217,-62.311],[16.253,-62.383],[16.325,-62.455],[16.577,-62.455],[16.793,-62.311],[16.793,-62.167],[16.577,-62.059],[16.469,-62.059],[16.325,-62.095],[16.217,-62.239]],"beached":false,"confidence":35}}},"threatens":{}},{"id":24,"island":"gp","centroid":[16.108,-61.866],"mass":0.11,"count":36,"hull":[[15.915,-61.829],[16.023,-62.009],[16.347,-61.937],[16.203,-61.793],[15.987,-61.793]],"drift":{"speed":1.4,"bearing":359,"predictions":{"6h":{"centroid":[16.166,-61.839],"hull":[[15.973,-61.802],[16.081,-61.982],[16.405,-61.91],[16.261,-61.766],[16.045,-61.766]],"beached":false,"confidence":75},"12h":{"centroid":[16.208,-61.797],"hull":[[16.015,-61.76],[16.123,-61.94],[16.447,-61.868],[16.303,-61.724],[16.087,-61.724]],"beached":false,"confidence":55},"24h":{"centroid":[16.39,-61.791],"hull":[[16.197,-61.754],[16.305,-61.934],[16.629,-61.862],[16.485,-61.718],[16.269,-61.718]],"beached":false,"confidence":35}}},"threatens":{"now":[{"id":"gp-grande-anse","km":11},{"id":"gp-malendure","km":12},{"id":"gp-deshaies","km":23}],"6h":[{"id":"gp-malendure","km":7},{"id":"gp-grande-anse","km":8},{"id":"gp-deshaies","km":16}],"12h":[{"id":"gp-malendure","km":5},{"id":"gp-grande-anse","km":9},{"id":"gp-deshaies","km":11},{"id":"gp-bas-du-fort","km":29}],"24h":[{"id":"gp-deshaies","km":9},{"id":"gp-malendure","km":24},{"id":"gp-moule","km":28},{"id":"gp-grande-anse","km":29}]}},{"id":25,"island":"gp","centroid":[16.068,-60.479],"mass":0.11,"count":13,"hull":[[15.959,-60.522],[16.139,-60.522],[16.139,-60.414],[16.067,-60.378],[15.995,-60.45]],"drift":{"speed":1.4,"bearing":359,"predictions":{"6h":{"centroid":[16.126,-60.452],"hull":[[16.017,-60.495],[16.197,-60.495],[16.197,-60.387],[16.125,-60.351],[16.053,-60.423]],"beached":false,"confidence":75},"12h":{"centroid":[16.168,-60.41],"hull":[[16.059,-60.453],[16.239,-60.453],[16.239,-60.345],[16.167,-60.309],[16.095,-60.381]],"beached":false,"confidence":55},"24h":{"centroid":[16.35,-60.404],"hull":[[16.241,-60.447],[16.421,-60.447],[16.421,-60.339],[16.349,-60.303],[16.277,-60.375]],"beached":false,"confidence":35}}},"threatens":{}},{"id":26,"island":"gp","centroid":[16.458,-61.092],"mass":0.11,"count":4,"hull":[[16.421,-61.084],[16.457,-61.12],[16.493,-61.084]],"drift":{"speed":1.4,"bearing":359,"predictions":{"6h":{"centroid":[16.516,-61.065],"hull":[[16.479,-61.057],[16.515,-61.093],[16.551,-61.057]],"beached":false,"confidence":75},"12h":{"centroid":[16.558,-61.023],"hull":[[16.521,-61.015],[16.557,-61.051],[16.593,-61.015]],"beached":false,"confidence":55},"24h":{"centroid":[16.74,-61.017],"hull":[[16.703,-61.009],[16.739,-61.045],[16.775,-61.009]],"beached":false,"confidence":35}}},"threatens":{"now":[{"id":"gp-vieux-fort","km":24},{"id":"gp-pt-chateaux","km":27}]}},{"id":27,"island":"gp","centroid":[16.459,-60.692],"mass":0.1,"count":30,"hull":[[16.277,-60.696],[16.349,-60.804],[16.529,-60.912],[16.637,-60.876],[16.529,-60.552],[16.457,-60.48],[16.313,-60.624]],"drift":{"speed":1.4,"bearing":359,"predictions":{"6h":{"centroid":[16.517,-60.665],"hull":[[16.335,-60.669],[16.407,-60.777],[16.587,-60.885],[16.695,-60.849],[16.587,-60.525],[16.515,-60.453],[16.371,-60.597]],"beached":false,"confidence":75},"12h":{"centroid":[16.559,-60.623],"hull":[[16.377,-60.627],[16.449,-60.735],[16.629,-60.843],[16.737,-60.807],[16.629,-60.483],[16.557,-60.411],[16.413,-60.555]],"beached":false,"confidence":55},"24h":{"centroid":[16.741,-60.617],"hull":[[16.559,-60.621],[16.631,-60.729],[16.811,-60.837],[16.919,-60.801],[16.811,-60.477],[16.739,-60.405],[16.595,-60.549]],"beached":false,"confidence":35}}},"threatens":{}},{"id":28,"island":"gp","centroid":[16.267,-60.188],"mass":0.1,"count":19,"hull":[[16.171,-60.148],[16.243,-60.292],[16.279,-60.292],[16.315,-60.256],[16.315,-60.076],[16.279,-60.04]],"drift":{"speed":1.4,"bearing":359,"predictions":{"6h":{"centroid":[16.325,-60.161],"hull":[[16.229,-60.121],[16.301,-60.265],[16.337,-60.265],[16.373,-60.229],[16.373,-60.049],[16.337,-60.013]],"beached":false,"confidence":75},"12h":{"centroid":[16.367,-60.119],"hull":[[16.271,-60.079],[16.343,-60.223],[16.379,-60.223],[16.415,-60.187],[16.415,-60.007],[16.379,-59.971]],"beached":false,"confidence":55},"24h":{"centroid":[16.549,-60.113],"hull":[[16.453,-60.073],[16.525,-60.217],[16.561,-60.217],[16.597,-60.181],[16.597,-60.001],[16.561,-59.965]],"beached":false,"confidence":35}}},"threatens":{}},{"id":29,"island":"gp","centroid":[16.883,-60.249],"mass":0.1,"count":9,"hull":[[16.768,-60.28],[16.876,-60.316],[16.984,-60.208],[16.912,-60.208],[16.804,-60.244]],"drift":{"speed":1.4,"bearing":359,"predictions":{"6h":{"centroid":[16.941,-60.222],"hull":[[16.826,-60.253],[16.934,-60.289],[17.042,-60.181],[16.97,-60.181],[16.862,-60.217]],"beached":false,"confidence":75},"12h":{"centroid":[16.983,-60.18],"hull":[[16.868,-60.211],[16.976,-60.247],[17.084,-60.139],[17.012,-60.139],[16.904,-60.175]],"beached":false,"confidence":55},"24h":{"centroid":[17.165,-60.174],"hull":[[17.05,-60.205],[17.158,-60.241],[17.266,-60.133],[17.194,-60.133],[17.086,-60.169]],"beached":false,"confidence":35}}},"threatens":{}},{"id":30,"island":"gp","centroid":[16.745,-60.84],"mass":0.1,"count":8,"hull":[[16.687,-60.846],[16.759,-60.918],[16.795,-60.846],[16.795,-60.81],[16.687,-60.774]],"drift":{"speed":1.4,"bearing":359,"predictions":{"6h":{"centroid":[16.803,-60.813],"hull":[[16.745,-60.819],[16.817,-60.891],[16.853,-60.819],[16.853,-60.783],[16.745,-60.747]],"beached":false,"confidence":75},"12h":{"centroid":[16.845,-60.771],"hull":[[16.787,-60.777],[16.859,-60.849],[16.895,-60.777],[16.895,-60.741],[16.787,-60.705]],"beached":false,"confidence":55},"24h":{"centroid":[17.027,-60.765],"hull":[[16.969,-60.771],[17.041,-60.843],[17.077,-60.771],[17.077,-60.735],[16.969,-60.699]],"beached":false,"confidence":35}}},"threatens":{}}]}