{"updatedAt":"2026-07-18T02:28:04.880Z","wind":{"florida":{"speed":10.5,"dir":333,"cloud_cover":36,"temperature":24.9,"precipitation":0,"uv_index":0,"hourly":[{"time":"2026-07-17T00:00","speed":5.2,"dir":282,"cloud_cover":100,"uv_index":0,"temperature":26.7,"precip_prob":29},{"time":"2026-07-17T01:00","speed":8.5,"dir":152,"cloud_cover":78,"uv_index":0,"temperature":26.6,"precip_prob":37},{"time":"2026-07-17T02:00","speed":4.7,"dir":337,"cloud_cover":43,"uv_index":0,"temperature":27,"precip_prob":28},{"time":"2026-07-17T03:00","speed":3.2,"dir":90,"cloud_cover":0,"uv_index":0,"temperature":26.1,"precip_prob":12},{"time":"2026-07-17T04:00","speed":3.1,"dir":126,"cloud_cover":1,"uv_index":0,"temperature":25.9,"precip_prob":2},{"time":"2026-07-17T05:00","speed":2.2,"dir":81,"cloud_cover":0,"uv_index":0,"temperature":26.2,"precip_prob":2},{"time":"2026-07-17T06:00","speed":1.8,"dir":143,"cloud_cover":22,"uv_index":0,"temperature":26.2,"precip_prob":1},{"time":"2026-07-17T07:00","speed":4,"dir":85,"cloud_cover":19,"uv_index":0,"temperature":26,"precip_prob":0},{"time":"2026-07-17T08:00","speed":2.1,"dir":121,"cloud_cover":0,"uv_index":0.4,"temperature":27.3,"precip_prob":0},{"time":"2026-07-17T09:00","speed":3.8,"dir":131,"cloud_cover":50,"uv_index":1.25,"temperature":29.4,"precip_prob":0},{"time":"2026-07-17T10:00","speed":5.4,"dir":278,"cloud_cover":24,"uv_index":3.8,"temperature":30.9,"precip_prob":0},{"time":"2026-07-17T11:00","speed":4.7,"dir":261,"cloud_cover":22,"uv_index":5.75,"temperature":31.8,"precip_prob":1},{"time":"2026-07-17T12:00","speed":8.9,"dir":223,"cloud_cover":19,"uv_index":6.95,"temperature":32.2,"precip_prob":2},{"time":"2026-07-17T13:00","speed":8.8,"dir":235,"cloud_cover":15,"uv_index":7.85,"temperature":33,"precip_prob":3},{"time":"2026-07-17T14:00","speed":10.8,"dir":201,"cloud_cover":35,"uv_index":7.45,"temperature":33.7,"precip_prob":5},{"time":"2026-07-17T15:00","speed":5.8,"dir":180,"cloud_cover":36,"uv_index":8.35,"temperature":33.9,"precip_prob":9},{"time":"2026-07-17T16:00","speed":7.3,"dir":261,"cloud_cover":73,"uv_index":7.25,"temperature":33.7,"precip_prob":14},{"time":"2026-07-17T17:00","speed":15.1,"dir":162,"cloud_cover":100,"uv_index":4,"temperature":33.2,"precip_prob":22},{"time":"2026-07-17T18:00","speed":18.2,"dir":98,"cloud_cover":100,"uv_index":3.65,"temperature":24.3,"precip_prob":45},{"time":"2026-07-17T19:00","speed":18.3,"dir":196,"cloud_cover":83,"uv_index":1.2,"temperature":24.9,"precip_prob":67},{"time":"2026-07-17T20:00","speed":2.9,"dir":187,"cloud_cover":100,"uv_index":0.25,"temperature":25.1,"precip_prob":60},{"time":"2026-07-17T21:00","speed":11.5,"dir":131,"cloud_cover":72,"uv_index":0,"temperature":25.2,"precip_prob":37},{"time":"2026-07-17T22:00","speed":7.9,"dir":313,"cloud_cover":44,"uv_index":0,"temperature":25.2,"precip_prob":18},{"time":"2026-07-17T23:00","speed":2,"dir":315,"cloud_cover":22,"uv_index":0,"temperature":24.6,"precip_prob":8},{"time":"2026-07-18T00:00","speed":3.3,"dir":49,"cloud_cover":100,"uv_index":0,"temperature":24.6,"precip_prob":2},{"time":"2026-07-18T01:00","speed":3.6,"dir":96,"cloud_cover":100,"uv_index":0,"temperature":24.7,"precip_prob":1},{"time":"2026-07-18T02:00","speed":3.5,"dir":114,"cloud_cover":100,"uv_index":0,"temperature":24.7,"precip_prob":1},{"time":"2026-07-18T03:00","speed":4.8,"dir":138,"cloud_cover":65,"uv_index":0,"temperature":24.7,"precip_prob":0},{"time":"2026-07-18T04:00","speed":3.8,"dir":131,"cloud_cover":100,"uv_index":0,"temperature":24.6,"precip_prob":0},{"time":"2026-07-18T05:00","speed":6.7,"dir":126,"cloud_cover":96,"uv_index":0,"temperature":24.6,"precip_prob":0},{"time":"2026-07-18T06:00","speed":6.1,"dir":130,"cloud_cover":100,"uv_index":0,"temperature":24.5,"precip_prob":0},{"time":"2026-07-18T07:00","speed":4,"dir":90,"cloud_cover":100,"uv_index":0,"temperature":24.5,"precip_prob":0},{"time":"2026-07-18T08:00","speed":6.2,"dir":144,"cloud_cover":100,"uv_index":0.5,"temperature":26.3,"precip_prob":1},{"time":"2026-07-18T09:00","speed":9.3,"dir":167,"cloud_cover":100,"uv_index":1.7,"temperature":27.9,"precip_prob":12},{"time":"2026-07-18T10:00","speed":11.2,"dir":165,"cloud_cover":100,"uv_index":3.6,"temperature":28.9,"precip_prob":5},{"time":"2026-07-18T11:00","speed":13.4,"dir":160,"cloud_cover":100,"uv_index":5.2,"temperature":28.2,"precip_prob":7},{"time":"2026-07-18T12:00","speed":15.5,"dir":162,"cloud_cover":100,"uv_index":4.45,"temperature":30.4,"precip_prob":11},{"time":"2026-07-18T13:00","speed":17.7,"dir":168,"cloud_cover":100,"uv_index":3.6,"temperature":31.9,"precip_prob":14},{"time":"2026-07-18T14:00","speed":16.9,"dir":168,"cloud_cover":100,"uv_index":7.1,"temperature":32.8,"precip_prob":11},{"time":"2026-07-18T15:00","speed":15.2,"dir":166,"cloud_cover":100,"uv_index":7.85,"temperature":33.3,"precip_prob":8},{"time":"2026-07-18T16:00","speed":15.8,"dir":163,"cloud_cover":100,"uv_index":6.9,"temperature":33.5,"precip_prob":8},{"time":"2026-07-18T17:00","speed":18.2,"dir":155,"cloud_cover":98,"uv_index":4.3,"temperature":33.1,"precip_prob":11},{"time":"2026-07-18T18:00","speed":15.1,"dir":155,"cloud_cover":94,"uv_index":2.8,"temperature":32,"precip_prob":10},{"time":"2026-07-18T19:00","speed":5.4,"dir":266,"cloud_cover":93,"uv_index":1.6,"temperature":30.6,"precip_prob":6},{"time":"2026-07-18T20:00","speed":7.9,"dir":336,"cloud_cover":100,"uv_index":0.4,"temperature":27.7,"precip_prob":7},{"time":"2026-07-18T21:00","speed":7.3,"dir":349,"cloud_cover":89,"uv_index":0,"temperature":26.8,"precip_prob":3},{"time":"2026-07-18T22:00","speed":6.2,"dir":54,"cloud_cover":90,"uv_index":0,"temperature":26.6,"precip_prob":2},{"time":"2026-07-18T23:00","speed":3.6,"dir":84,"cloud_cover":100,"uv_index":0,"temperature":26.6,"precip_prob":1},{"time":"2026-07-19T00:00","speed":4,"dir":90,"cloud_cover":100,"uv_index":0,"temperature":26.4,"precip_prob":1},{"time":"2026-07-19T01:00","speed":4.7,"dir":90,"cloud_cover":100,"uv_index":0,"temperature":26.1,"precip_prob":0},{"time":"2026-07-19T02:00","speed":5.9,"dir":133,"cloud_cover":100,"uv_index":0,"temperature":25.7,"precip_prob":0},{"time":"2026-07-19T03:00","speed":5.6,"dir":135,"cloud_cover":72,"uv_index":0,"temperature":25.4,"precip_prob":1},{"time":"2026-07-19T04:00","speed":5.6,"dir":153,"cloud_cover":22,"uv_index":0,"temperature":25.2,"precip_prob":1},{"time":"2026-07-19T05:00","speed":6.3,"dir":156,"cloud_cover":18,"uv_index":0,"temperature":25.2,"precip_prob":2},{"time":"2026-07-19T06:00","speed":6.8,"dir":108,"cloud_cover":0,"uv_index":0,"temperature":24.8,"precip_prob":2},{"time":"2026-07-19T07:00","speed":6.3,"dir":103,"cloud_cover":1,"uv_index":0,"temperature":24.4,"precip_prob":2},{"time":"2026-07-19T08:00","speed":12.1,"dir":163,"cloud_cover":7,"uv_index":0.55,"temperature":26.7,"precip_prob":1},{"time":"2026-07-19T09:00","speed":16.2,"dir":159,"cloud_cover":1,"uv_index":1.95,"temperature":28.3,"precip_prob":5},{"time":"2026-07-19T10:00","speed":15.8,"dir":163,"cloud_cover":9,"uv_index":3.85,"temperature":30,"precip_prob":5},{"time":"2026-07-19T11:00","speed":18.2,"dir":171,"cloud_cover":18,"uv_index":5.8,"temperature":31,"precip_prob":5},{"time":"2026-07-19T12:00","speed":17.5,"dir":161,"cloud_cover":72,"uv_index":7.4,"temperature":32.5,"precip_prob":5},{"time":"2026-07-19T13:00","speed":16.2,"dir":163,"cloud_cover":100,"uv_index":8.5,"temperature":33.5,"precip_prob":5},{"time":"2026-07-19T14:00","speed":16.1,"dir":153,"cloud_cover":100,"uv_index":8.8,"temperature":34.2,"precip_prob":5},{"time":"2026-07-19T15:00","speed":23.7,"dir":242,"cloud_cover":100,"uv_index":8.4,"temperature":32.4,"precip_prob":56},{"time":"2026-07-19T16:00","speed":13.1,"dir":238,"cloud_cover":58,"uv_index":7.15,"temperature":31.5,"precip_prob":56},{"time":"2026-07-19T17:00","speed":30.2,"dir":171,"cloud_cover":99,"uv_index":3.45,"temperature":27.3,"precip_prob":56},{"time":"2026-07-19T18:00","speed":16.3,"dir":144,"cloud_cover":100,"uv_index":2.9,"temperature":29.2,"precip_prob":56},{"time":"2026-07-19T19:00","speed":6.3,"dir":146,"cloud_cover":97,"uv_index":1.05,"temperature":28.7,"precip_prob":56},{"time":"2026-07-19T20:00","speed":3.8,"dir":298,"cloud_cover":100,"uv_index":0.25,"temperature":28,"precip_prob":56},{"time":"2026-07-19T21:00","speed":0.5,"dir":45,"cloud_cover":100,"uv_index":0,"temperature":28.2,"precip_prob":12},{"time":"2026-07-19T22:00","speed":1.9,"dir":292,"cloud_cover":100,"uv_index":0,"temperature":27.8,"precip_prob":12},{"time":"2026-07-19T23:00","speed":1.5,"dir":194,"cloud_cover":100,"uv_index":0,"temperature":27.6,"precip_prob":12},{"time":"2026-07-20T00:00","speed":4.8,"dir":167,"cloud_cover":100,"uv_index":0,"temperature":27.2,"precip_prob":12},{"time":"2026-07-20T01:00","speed":5.9,"dir":166,"cloud_cover":100,"uv_index":0,"temperature":26.6,"precip_prob":12},{"time":"2026-07-20T02:00","speed":5.1,"dir":172,"cloud_cover":100,"uv_index":0,"temperature":25.7,"precip_prob":12},{"time":"2026-07-20T03:00","speed":4.7,"dir":157,"cloud_cover":100,"uv_index":0,"temperature":25.3,"precip_prob":1},{"time":"2026-07-20T04:00","speed":5.2,"dir":146,"cloud_cover":100,"uv_index":0,"temperature":25,"precip_prob":1},{"time":"2026-07-20T05:00","speed":5.7,"dir":162,"cloud_cover":100,"uv_index":0,"temperature":24.9,"precip_prob":1},{"time":"2026-07-20T06:00","speed":5.4,"dir":184,"cloud_cover":100,"uv_index":0,"temperature":24.7,"precip_prob":1},{"time":"2026-07-20T07:00","speed":4.4,"dir":189,"cloud_cover":100,"uv_index":0,"temperature":24.6,"precip_prob":1},{"time":"2026-07-20T08:00","speed":3.2,"dir":180,"cloud_cover":100,"uv_index":0.5,"temperature":26.4,"precip_prob":1},{"time":"2026-07-20T09:00","speed":5.6,"dir":165,"cloud_cover":100,"uv_index":1.85,"temperature":28.6,"precip_prob":8},{"time":"2026-07-20T10:00","speed":8.3,"dir":180,"cloud_cover":100,"uv_index":3.7,"temperature":30.6,"precip_prob":8},{"time":"2026-07-20T11:00","speed":9.7,"dir":184,"cloud_cover":100,"uv_index":5.6,"temperature":32.6,"precip_prob":8},{"time":"2026-07-20T12:00","speed":10.5,"dir":188,"cloud_cover":81,"uv_index":7.25,"temperature":34.1,"precip_prob":8},{"time":"2026-07-20T13:00","speed":10,"dir":195,"cloud_cover":67,"uv_index":8.5,"temperature":35.3,"precip_prob":8},{"time":"2026-07-20T14:00","speed":9.8,"dir":188,"cloud_cover":37,"uv_index":8.85,"temperature":36.1,"precip_prob":8},{"time":"2026-07-20T15:00","speed":8.6,"dir":178,"cloud_cover":16,"uv_index":8.45,"temperature":36.7,"precip_prob":57},{"time":"2026-07-20T16:00","speed":8.3,"dir":146,"cloud_cover":16,"uv_index":7.35,"temperature":36.9,"precip_prob":57},{"time":"2026-07-20T17:00","speed":15,"dir":117,"cloud_cover":72,"uv_index":4.6,"temperature":35.1,"precip_prob":57},{"time":"2026-07-20T18:00","speed":15.5,"dir":118,"cloud_cover":100,"uv_index":1.25,"temperature":31.4,"precip_prob":57},{"time":"2026-07-20T19:00","speed":13,"dir":146,"cloud_cover":100,"uv_index":0.65,"temperature":30.4,"precip_prob":57},{"time":"2026-07-20T20:00","speed":12.1,"dir":197,"cloud_cover":100,"uv_index":0.05,"temperature":29,"precip_prob":57},{"time":"2026-07-20T21:00","speed":11.3,"dir":217,"cloud_cover":100,"uv_index":0,"temperature":28.2,"precip_prob":6},{"time":"2026-07-20T22:00","speed":9.7,"dir":231,"cloud_cover":100,"uv_index":0,"temperature":28.1,"precip_prob":6},{"time":"2026-07-20T23:00","speed":6.8,"dir":238,"cloud_cover":100,"uv_index":0,"temperature":28,"precip_prob":6},{"time":"2026-07-21T00:00","speed":4.7,"dir":184,"cloud_cover":100,"uv_index":0,"temperature":27.7,"precip_prob":6},{"time":"2026-07-21T01:00","speed":6.4,"dir":164,"cloud_cover":18,"uv_index":0,"temperature":26.4,"precip_prob":6},{"time":"2026-07-21T02:00","speed":5.9,"dir":169,"cloud_cover":0,"uv_index":0,"temperature":25.9,"precip_prob":6},{"time":"2026-07-21T03:00","speed":5,"dir":180,"cloud_cover":0,"uv_index":0,"temperature":25.6,"precip_prob":0},{"time":"2026-07-21T04:00","speed":3.1,"dir":201,"cloud_cover":5,"uv_index":0,"temperature":25.3,"precip_prob":0},{"time":"2026-07-21T05:00","speed":2.6,"dir":164,"cloud_cover":5,"uv_index":0,"temperature":25,"precip_prob":0},{"time":"2026-07-21T06:00","speed":4.1,"dir":135,"cloud_cover":35,"uv_index":0,"temperature":24.9,"precip_prob":0},{"time":"2026-07-21T07:00","speed":3.1,"dir":111,"cloud_cover":6,"uv_index":0,"temperature":25.1,"precip_prob":0},{"time":"2026-07-21T08:00","speed":1.8,"dir":101,"cloud_cover":10,"uv_index":0.55,"temperature":27.1,"precip_prob":0},{"time":"2026-07-21T09:00","speed":4.5,"dir":166,"cloud_cover":11,"uv_index":1.95,"temperature":28.7,"precip_prob":6},{"time":"2026-07-21T10:00","speed":7.3,"dir":189,"cloud_cover":44,"uv_index":3.8,"temperature":30.1,"precip_prob":6},{"time":"2026-07-21T11:00","speed":7.6,"dir":183,"cloud_cover":35,"uv_index":5.6,"temperature":31.7,"precip_prob":6},{"time":"2026-07-21T12:00","speed":7.5,"dir":163,"cloud_cover":59,"uv_index":6.3,"temperature":33,"precip_prob":6},{"time":"2026-07-21T13:00","speed":10.3,"dir":144,"cloud_cover":87,"uv_index":8.15,"temperature":34.5,"precip_prob":6},{"time":"2026-07-21T14:00","speed":11.7,"dir":137,"cloud_cover":76,"uv_index":7.85,"temperature":35.3,"precip_prob":6},{"time":"2026-07-21T15:00","speed":10.6,"dir":125,"cloud_cover":0,"uv_index":8.4,"temperature":35.7,"precip_prob":25},{"time":"2026-07-21T16:00","speed":9.1,"dir":124,"cloud_cover":0,"uv_index":7.35,"temperature":35.8,"precip_prob":25},{"time":"2026-07-21T17:00","speed":9.6,"dir":124,"cloud_cover":0,"uv_index":5.7,"temperature":35.5,"precip_prob":25},{"time":"2026-07-21T18:00","speed":12.5,"dir":123,"cloud_cover":0,"uv_index":3.75,"temperature":34.5,"precip_prob":25},{"time":"2026-07-21T19:00","speed":15,"dir":125,"cloud_cover":6,"uv_index":1.85,"temperature":32.2,"precip_prob":25},{"time":"2026-07-21T20:00","speed":14.6,"dir":130,"cloud_cover":0,"uv_index":0.5,"temperature":29.2,"precip_prob":25},{"time":"2026-07-21T21:00","speed":14.1,"dir":122,"cloud_cover":5,"uv_index":0,"temperature":28.4,"precip_prob":4},{"time":"2026-07-21T22:00","speed":9.7,"dir":141,"cloud_cover":6,"uv_index":0,"temperature":27.4,"precip_prob":4},{"time":"2026-07-21T23:00","speed":9,"dir":175,"cloud_cover":100,"uv_index":0,"temperature":26.8,"precip_prob":4},{"time":"2026-07-22T00:00","speed":7.4,"dir":151,"cloud_cover":100,"uv_index":0,"temperature":26.3,"precip_prob":4},{"time":"2026-07-22T01:00","speed":7.7,"dir":143,"cloud_cover":100,"uv_index":0,"temperature":25.9,"precip_prob":4},{"time":"2026-07-22T02:00","speed":7.3,"dir":147,"cloud_cover":89,"uv_index":0,"temperature":25.7,"precip_prob":4},{"time":"2026-07-22T03:00","speed":5.5,"dir":148,"cloud_cover":12,"uv_index":0,"temperature":25.3,"precip_prob":2},{"time":"2026-07-22T04:00","speed":3.9,"dir":158,"cloud_cover":11,"uv_index":0,"temperature":25.1,"precip_prob":2},{"time":"2026-07-22T05:00","speed":4.1,"dir":165,"cloud_cover":5,"uv_index":0,"temperature":24.9,"precip_prob":2},{"time":"2026-07-22T06:00","speed":1.8,"dir":143,"cloud_cover":43,"uv_index":0,"temperature":24.8,"precip_prob":2},{"time":"2026-07-22T07:00","speed":1.8,"dir":79,"cloud_cover":69,"uv_index":0,"temperature":24.9,"precip_prob":2},{"time":"2026-07-22T08:00","speed":2.4,"dir":63,"cloud_cover":7,"uv_index":0.55,"temperature":27.1,"precip_prob":2},{"time":"2026-07-22T09:00","speed":5.9,"dir":133,"cloud_cover":47,"uv_index":1.95,"temperature":29.3,"precip_prob":5},{"time":"2026-07-22T10:00","speed":6.8,"dir":155,"cloud_cover":95,"uv_index":3.8,"temperature":31.1,"precip_prob":5},{"time":"2026-07-22T11:00","speed":6.4,"dir":153,"cloud_cover":7,"uv_index":5.75,"temperature":32.8,"precip_prob":5},{"time":"2026-07-22T12:00","speed":5.2,"dir":146,"cloud_cover":19,"uv_index":7.4,"temperature":34.5,"precip_prob":5},{"time":"2026-07-22T13:00","speed":4.7,"dir":148,"cloud_cover":58,"uv_index":8.45,"temperature":35.9,"precip_prob":5},{"time":"2026-07-22T14:00","speed":3.9,"dir":158,"cloud_cover":60,"uv_index":8.8,"temperature":36.6,"precip_prob":5},{"time":"2026-07-22T15:00","speed":2.3,"dir":18,"cloud_cover":76,"uv_index":7.25,"temperature":34.8,"precip_prob":19},{"time":"2026-07-22T16:00","speed":9.4,"dir":358,"cloud_cover":90,"uv_index":4.8,"temperature":31.9,"precip_prob":19},{"time":"2026-07-22T17:00","speed":12.6,"dir":358,"cloud_cover":100,"uv_index":2.75,"temperature":29.7,"precip_prob":19},{"time":"2026-07-22T18:00","speed":8,"dir":10,"cloud_cover":100,"uv_index":1.45,"temperature":29,"precip_prob":19},{"time":"2026-07-22T19:00","speed":4.4,"dir":99,"cloud_cover":100,"uv_index":0.6,"temperature":29.1,"precip_prob":19},{"time":"2026-07-22T20:00","speed":9.4,"dir":140,"cloud_cover":100,"uv_index":0.15,"temperature":29.1,"precip_prob":19},{"time":"2026-07-22T21:00","speed":11.1,"dir":144,"cloud_cover":100,"uv_index":0,"temperature":28.6,"precip_prob":2},{"time":"2026-07-22T22:00","speed":11.1,"dir":144,"cloud_cover":100,"uv_index":0,"temperature":28,"precip_prob":2},{"time":"2026-07-22T23:00","speed":9.9,"dir":147,"cloud_cover":100,"uv_index":0,"temperature":27.5,"precip_prob":2},{"time":"2026-07-23T00:00","speed":8,"dir":153,"cloud_cover":92,"uv_index":0,"temperature":27,"precip_prob":2},{"time":"2026-07-23T01:00","speed":5.5,"dir":169,"cloud_cover":80,"uv_index":0,"temperature":26.6,"precip_prob":2},{"time":"2026-07-23T02:00","speed":4,"dir":190,"cloud_cover":67,"uv_index":0,"temperature":26.3,"precip_prob":2},{"time":"2026-07-23T03:00","speed":3.4,"dir":212,"cloud_cover":51,"uv_index":0,"temperature":25.8,"precip_prob":2},{"time":"2026-07-23T04:00","speed":2.8,"dir":230,"cloud_cover":34,"uv_index":0,"temperature":25.4,"precip_prob":2},{"time":"2026-07-23T05:00","speed":2.4,"dir":243,"cloud_cover":21,"uv_index":0,"temperature":25.3,"precip_prob":2},{"time":"2026-07-23T06:00","speed":2.2,"dir":261,"cloud_cover":14,"uv_index":0,"temperature":25.5,"precip_prob":2},{"time":"2026-07-23T07:00","speed":1.8,"dir":270,"cloud_cover":11,"uv_index":0,"temperature":25.9,"precip_prob":2},{"time":"2026-07-23T08:00","speed":1.5,"dir":284,"cloud_cover":13,"uv_index":0.6,"temperature":26.9,"precip_prob":2},{"time":"2026-07-23T09:00","speed":0.7,"dir":360,"cloud_cover":25,"uv_index":1.7,"temperature":28.6,"precip_prob":4},{"time":"2026-07-23T10:00","speed":1.8,"dir":53,"cloud_cover":43,"uv_index":3.25,"temperature":30.8,"precip_prob":4},{"time":"2026-07-23T11:00","speed":3.1,"dir":45,"cloud_cover":51,"uv_index":5,"temperature":32.7,"precip_prob":4},{"time":"2026-07-23T12:00","speed":4.4,"dir":9,"cloud_cover":40,"uv_index":6.65,"temperature":33.9,"precip_prob":4},{"time":"2026-07-23T13:00","speed":7.3,"dir":349,"cloud_cover":21,"uv_index":7.95,"temperature":34.8,"precip_prob":4},{"time":"2026-07-23T14:00","speed":9.4,"dir":342,"cloud_cover":7,"uv_index":8.65,"temperature":35.5,"precip_prob":4},{"time":"2026-07-23T15:00","speed":10.3,"dir":348,"cloud_cover":3,"uv_index":8.55,"temperature":36,"precip_prob":21},{"time":"2026-07-23T16:00","speed":10.1,"dir":356,"cloud_cover":5,"uv_index":7.75,"temperature":36.3,"precip_prob":21},{"time":"2026-07-23T17:00","speed":9.1,"dir":9,"cloud_cover":16,"uv_index":6.15,"temperature":35.9,"precip_prob":21},{"time":"2026-07-23T18:00","speed":7.4,"dir":43,"cloud_cover":42,"uv_index":4,"temperature":34,"precip_prob":21},{"time":"2026-07-23T19:00","speed":9,"dir":90,"cloud_cover":75,"uv_index":1.95,"temperature":31.4,"precip_prob":21},{"time":"2026-07-23T20:00","speed":11.8,"dir":110,"cloud_cover":100,"uv_index":0.6,"temperature":29.3,"precip_prob":21},{"time":"2026-07-23T21:00","speed":11.2,"dir":123,"cloud_cover":100,"uv_index":0,"temperature":28.2,"precip_prob":4},{"time":"2026-07-23T22:00","speed":9.5,"dir":143,"cloud_cover":100,"uv_index":0,"temperature":27.6,"precip_prob":4},{"time":"2026-07-23T23:00","speed":8.6,"dir":158,"cloud_cover":100,"uv_index":0,"temperature":27.2,"precip_prob":4}]}},"bankCount":15,"banks":[{"id":1,"island":"florida","centroid":[27.915,-81.273],"mass":0.32,"count":15,"hull":[[27.838,-81.22],[27.865,-81.301],[27.956,-81.347],[27.973,-81.328],[27.992,-81.311],[27.956,-81.239],[27.892,-81.22]],"drift":{"speed":0.5,"bearing":239,"predictions":{"6h":{"centroid":[27.916,-81.311],"hull":[[27.839,-81.258],[27.887,-81.31],[27.947,-81.357],[27.948,-81.325],[27.973,-81.33],[27.957,-81.277],[27.893,-81.258]],"beached":false,"confidence":75},"12h":{"centroid":[27.921,-81.345],"hull":[[27.862,-81.287],[27.896,-81.315],[27.941,-81.355],[27.951,-81.344],[27.998,-81.383],[27.962,-81.311],[27.898,-81.292]],"beached":false,"confidence":55},"24h":{"centroid":[27.952,-81.399],"hull":[[27.898,-81.304],[27.911,-81.322],[27.948,-81.357],[27.955,-81.349],[27.963,-81.342],[27.973,-81.342],[27.929,-81.346]],"beached":false,"confidence":35},"48h":{"centroid":[27.99,-81.57],"hull":[[27.915,-81.316],[27.918,-81.316],[27.936,-81.339],[27.947,-81.357],[27.951,-81.352],[27.952,-81.356],[27.931,-81.35]],"beached":false,"confidence":22},"72h":{"centroid":[28.041,-81.722],"hull":[[27.922,-81.326],[27.923,-81.321],[27.937,-81.343],[27.94,-81.34],[27.942,-81.338],[27.945,-81.347],[27.933,-81.343]],"beached":false,"confidence":14}}},"threatens":{}},{"id":2,"island":"florida","centroid":[28.744,-80.715],"mass":0.32,"count":6,"hull":[[28.69,-80.703],[28.726,-80.739],[28.762,-80.739],[28.798,-80.703]],"drift":{"speed":0.5,"bearing":239,"predictions":{"6h":{"centroid":[28.745,-80.753],"hull":[[28.722,-80.726],[28.737,-80.741],[28.763,-80.777],[28.799,-80.741]],"beached":false,"confidence":75},"12h":{"centroid":[28.75,-80.788],"hull":[[28.724,-80.741],[28.739,-80.756],[28.758,-80.77],[28.804,-80.776]],"beached":false,"confidence":55},"24h":{"centroid":[28.781,-80.842],"hull":[[28.739,-80.751],[28.752,-80.779],[28.767,-80.779],[28.835,-80.83]],"beached":false,"confidence":35},"48h":{"centroid":[28.819,-81.015],"hull":[[28.747,-80.753],[28.754,-80.773],[28.761,-80.773],[28.775,-80.783]],"beached":false,"confidence":22},"72h":{"centroid":[28.87,-81.168],"hull":[[28.754,-80.774],[28.758,-80.779],[28.763,-80.779],[28.768,-80.774]],"beached":false,"confidence":14}}},"threatens":{}},{"id":3,"island":"florida","centroid":[28.225,-81.401],"mass":0.32,"count":5,"hull":[[28.182,-81.358],[28.218,-81.43],[28.254,-81.43],[28.254,-81.394]],"drift":{"speed":0.5,"bearing":239,"predictions":{"6h":{"centroid":[28.226,-81.439],"hull":[[28.201,-81.398],[28.222,-81.429],[28.238,-81.429],[28.255,-81.432]],"beached":false,"confidence":75},"12h":{"centroid":[28.231,-81.473],"hull":[[28.197,-81.423],[28.225,-81.425],[28.233,-81.425],[28.24,-81.428]],"beached":false,"confidence":55},"24h":{"centroid":[28.262,-81.527],"hull":[[28.223,-81.427],[28.23,-81.429],[28.237,-81.429],[28.241,-81.429]],"beached":false,"confidence":35},"48h":{"centroid":[28.3,-81.699],"hull":[[28.228,-81.427],[28.232,-81.434],[28.235,-81.434],[28.235,-81.43]],"beached":false,"confidence":22},"72h":{"centroid":[28.351,-81.852],"hull":[[28.233,-81.442],[28.237,-81.449],[28.241,-81.449],[28.241,-81.445]],"beached":false,"confidence":14}}},"threatens":{}},{"id":4,"island":"florida","centroid":[27.821,-81.41],"mass":0.32,"count":4,"hull":[[27.795,-81.428],[27.856,-81.423],[27.831,-81.392],[27.795,-81.392]],"drift":{"speed":0.5,"bearing":239,"predictions":{"6h":{"centroid":[27.822,-81.448],"hull":[[27.807,-81.441],[27.841,-81.439],[27.832,-81.43],[27.796,-81.43]],"beached":false,"confidence":75},"12h":{"centroid":[27.827,-81.482],"hull":[[27.815,-81.438],[27.838,-81.446],[27.83,-81.44],[27.81,-81.44]],"beached":false,"confidence":55},"24h":{"centroid":[27.858,-81.536],"hull":[[27.824,-81.444],[27.838,-81.443],[27.836,-81.444],[27.824,-81.444]],"beached":false,"confidence":35},"48h":{"centroid":[27.896,-81.707],"hull":[[27.826,-81.442],[27.832,-81.441],[27.832,-81.447],[27.828,-81.447]],"beached":false,"confidence":22},"72h":{"centroid":[27.947,-81.859],"hull":[[27.831,-81.457],[27.837,-81.456],[27.835,-81.453],[27.831,-81.453]],"beached":false,"confidence":14}}},"threatens":{}},{"id":5,"island":"florida","centroid":[28.032,-81.395],"mass":0.32,"count":4,"hull":[[28.004,-81.395],[28.04,-81.431],[28.04,-81.359]],"drift":{"speed":0.5,"bearing":239,"predictions":{"6h":{"centroid":[28.033,-81.433],"hull":[[28.017,-81.416],[28.037,-81.437],[28.041,-81.397]],"beached":false,"confidence":75},"12h":{"centroid":[28.038,-81.467],"hull":[[28.023,-81.425],[28.038,-81.441],[28.046,-81.431]],"beached":false,"confidence":55},"24h":{"centroid":[28.069,-81.521],"hull":[[28.035,-81.435],[28.046,-81.446],[28.057,-81.446]],"beached":false,"confidence":35},"48h":{"centroid":[28.107,-81.693],"hull":[[28.038,-81.435],[28.047,-81.454],[28.052,-81.457]],"beached":false,"confidence":22},"72h":{"centroid":[28.158,-81.845],"hull":[[28.042,-81.44],[28.05,-81.46],[28.05,-81.45]],"beached":false,"confidence":14}}},"threatens":{}},{"id":6,"island":"florida","centroid":[29.936,-81.612],"mass":0.31,"count":19,"hull":[[29.795,-81.552],[29.82,-81.604],[30.038,-81.714],[30.108,-81.712],[29.984,-81.579]],"drift":{"speed":0.5,"bearing":239,"predictions":{"6h":{"centroid":[29.937,-81.65],"hull":[[29.831,-81.595],[29.887,-81.625],[29.946,-81.626],[30.109,-81.75],[29.985,-81.617]],"beached":false,"confidence":75},"12h":{"centroid":[29.942,-81.685],"hull":[[29.879,-81.617],[29.91,-81.627],[29.947,-81.63],[30.114,-81.785],[29.941,-81.616]],"beached":false,"confidence":55},"24h":{"centroid":[29.973,-81.741],"hull":[[29.917,-81.624],[29.928,-81.624],[29.95,-81.635],[30.145,-81.841],[29.945,-81.622]],"beached":false,"confidence":35},"48h":{"centroid":[30.011,-81.915],"hull":[[29.929,-81.636],[29.932,-81.642],[30.113,-82.017],[30.183,-82.015],[29.948,-81.639]],"beached":false,"confidence":22},"72h":{"centroid":[30.062,-82.07],"hull":[[29.934,-81.652],[29.937,-81.657],[30.164,-82.172],[30.234,-82.17],[30.11,-82.037]],"beached":false,"confidence":14}}},"threatens":{}},{"id":7,"island":"florida","centroid":[27.387,-81.297],"mass":0.3,"count":6,"hull":[[27.353,-81.304],[27.407,-81.331],[27.413,-81.271],[27.377,-81.271]],"drift":{"speed":0.5,"bearing":239,"predictions":{"6h":{"centroid":[27.388,-81.334],"hull":[[27.377,-81.311],[27.399,-81.337],[27.414,-81.308],[27.378,-81.308]],"beached":false,"confidence":75},"12h":{"centroid":[27.393,-81.369],"hull":[[27.382,-81.311],[27.398,-81.342],[27.411,-81.331],[27.386,-81.312]],"beached":false,"confidence":55},"24h":{"centroid":[27.424,-81.422],"hull":[[27.388,-81.353],[27.401,-81.335],[27.414,-81.339],[27.398,-81.339]],"beached":false,"confidence":35},"48h":{"centroid":[27.462,-81.593],"hull":[[27.394,-81.351],[27.4,-81.341],[27.4,-81.333],[27.399,-81.345]],"beached":false,"confidence":22},"72h":{"centroid":[27.513,-81.744],"hull":[[27.396,-81.342],[27.402,-81.345],[27.402,-81.339],[27.399,-81.339]],"beached":false,"confidence":14}}},"threatens":{}},{"id":8,"island":"florida","centroid":[26.804,-80.858],"mass":0.28,"count":9,"hull":[[26.755,-80.828],[26.846,-80.926],[26.882,-80.926],[26.882,-80.89],[26.774,-80.782],[26.738,-80.782]],"drift":{"speed":0.5,"bearing":239,"predictions":{"6h":{"centroid":[26.805,-80.895],"hull":[[26.768,-80.863],[26.836,-80.937],[26.863,-80.937],[26.883,-80.927],[26.775,-80.819],[26.755,-80.829]],"beached":false,"confidence":75},"12h":{"centroid":[26.81,-80.929],"hull":[[26.786,-80.875],[26.831,-80.936],[26.851,-80.936],[26.867,-80.935],[26.78,-80.853],[26.759,-80.854]],"beached":false,"confidence":55},"24h":{"centroid":[26.841,-80.983],"hull":[[26.797,-80.911],[26.883,-81.051],[26.84,-80.919],[26.853,-80.924],[26.811,-80.907],[26.788,-80.886]],"beached":false,"confidence":35},"48h":{"centroid":[26.879,-81.153],"hull":[[26.81,-80.921],[26.825,-80.923],[26.831,-80.923],[26.89,-81.042],[26.818,-80.927],[26.806,-80.91]],"beached":false,"confidence":22},"72h":{"centroid":[26.93,-81.303],"hull":[[26.818,-80.932],[26.826,-80.926],[26.831,-80.926],[26.831,-80.922],[26.821,-80.924],[26.812,-80.907]],"beached":false,"confidence":14}}},"threatens":{}},{"id":9,"island":"florida","centroid":[25.075,-80.92],"mass":0.26,"count":14,"hull":[[25.031,-80.986],[25.067,-81.022],[25.15,-80.861],[25.067,-80.842],[25.031,-80.914]],"drift":{"speed":0.5,"bearing":239,"predictions":{"6h":{"centroid":[25.076,-80.957],"hull":[[25.043,-80.997],[25.07,-81.024],[25.099,-80.913],[25.068,-80.879],[25.032,-80.951]],"beached":false,"confidence":75},"12h":{"centroid":[25.081,-80.99],"hull":[[25.054,-80.996],[25.074,-81.017],[25.101,-80.923],[25.073,-80.912],[25.037,-80.984]],"beached":false,"confidence":55},"24h":{"centroid":[25.112,-81.043],"hull":[[25.071,-81.026],[25.084,-80.991],[25.102,-80.935],[25.091,-80.945],[25.07,-81.008]],"beached":false,"confidence":35},"48h":{"centroid":[25.15,-81.21],"hull":[[25.082,-81.004],[25.142,-81.312],[25.095,-80.951],[25.087,-80.958],[25.085,-81.01]],"beached":false,"confidence":22},"72h":{"centroid":[25.201,-81.358],"hull":[[25.157,-81.424],[25.193,-81.46],[25.276,-81.299],[25.193,-81.28],[25.157,-81.352]],"beached":false,"confidence":14}}},"threatens":{}},{"id":10,"island":"florida","centroid":[28.726,-80.671],"mass":0.26,"count":7,"hull":[[28.675,-80.675],[28.802,-80.676],[28.73,-80.64],[28.694,-80.64]],"drift":{"speed":0.5,"bearing":239,"predictions":{"6h":{"centroid":[28.727,-80.709],"hull":[[28.688,-80.702],[28.803,-80.714],[28.731,-80.678],[28.695,-80.678]],"beached":false,"confidence":75},"12h":{"centroid":[28.732,-80.744],"hull":[[28.701,-80.714],[28.808,-80.749],[28.736,-80.713],[28.7,-80.713]],"beached":false,"confidence":55},"24h":{"centroid":[28.763,-80.798],"hull":[[28.72,-80.726],[28.839,-80.803],[28.767,-80.767],[28.729,-80.725]],"beached":false,"confidence":35},"48h":{"centroid":[28.801,-80.971],"hull":[[28.73,-80.725],[28.79,-80.8],[28.759,-80.784],[28.74,-80.756]],"beached":false,"confidence":22},"72h":{"centroid":[28.852,-81.124],"hull":[[28.782,-81.014],[28.774,-80.78],[28.757,-80.771],[28.743,-80.746]],"beached":false,"confidence":14}}},"threatens":{}},{"id":11,"island":"florida","centroid":[28.533,-80.747],"mass":0.26,"count":4,"hull":[[28.48,-80.733],[28.552,-80.769],[28.574,-80.764],[28.552,-80.733]],"drift":{"speed":0.5,"bearing":239,"predictions":{"6h":{"centroid":[28.534,-80.785],"hull":[[28.511,-80.757],[28.544,-80.781],[28.557,-80.778],[28.553,-80.771]],"beached":false,"confidence":75},"12h":{"centroid":[28.539,-80.819],"hull":[[28.513,-80.771],[28.544,-80.787],[28.553,-80.785],[28.547,-80.78]],"beached":false,"confidence":55},"24h":{"centroid":[28.57,-80.874],"hull":[[28.531,-80.758],[28.546,-80.782],[28.552,-80.781],[28.551,-80.783]],"beached":false,"confidence":35},"48h":{"centroid":[28.608,-81.046],"hull":[[28.535,-80.776],[28.542,-80.779],[28.545,-80.779],[28.546,-80.785]],"beached":false,"confidence":22},"72h":{"centroid":[28.659,-81.199],"hull":[[28.54,-80.791],[28.548,-80.794],[28.55,-80.794],[28.548,-80.791]],"beached":false,"confidence":14}}},"threatens":{"now":[{"id":"fl010","km":27}],"6h":[{"id":"fl010","km":29}]}},{"id":12,"island":"florida","centroid":[27.005,-80.75],"mass":0.25,"count":69,"hull":[[26.829,-80.736],[26.95,-80.948],[27.018,-80.898],[27.153,-80.817],[27.153,-80.763],[27.099,-80.709],[27.072,-80.682],[26.954,-80.659]],"drift":{"speed":0.5,"bearing":239,"predictions":{"6h":{"centroid":[27.006,-80.787],"hull":[[26.83,-80.773],[26.965,-80.926],[27.019,-80.935],[27.117,-80.828],[27.154,-80.8],[27.1,-80.746],[27.073,-80.719],[26.955,-80.696]],"beached":false,"confidence":75},"12h":{"centroid":[27.011,-80.821],"hull":[[26.835,-80.807],[26.968,-80.952],[27.019,-80.914],[27.092,-80.828],[27.159,-80.834],[27.105,-80.78],[27.078,-80.753],[26.96,-80.73]],"beached":false,"confidence":55},"24h":{"centroid":[27.042,-80.875],"hull":[[26.866,-80.861],[26.995,-80.932],[27.033,-80.904],[27.083,-80.831],[27.109,-80.828],[27.136,-80.834],[27.109,-80.807],[26.991,-80.784]],"beached":false,"confidence":35},"48h":{"centroid":[27.08,-81.045],"hull":[[26.929,-80.961],[27.011,-80.906],[27.033,-80.89],[27.058,-80.836],[27.076,-80.847],[27.058,-80.83],[27.065,-80.846],[27.023,-80.903]],"beached":false,"confidence":22},"72h":{"centroid":[27.131,-81.196],"hull":[[26.984,-80.932],[27.022,-80.903],[27.038,-80.891],[27.07,-80.872],[27.07,-80.859],[27.057,-80.846],[27.066,-80.87],[27.037,-80.9]],"beached":false,"confidence":14}}},"threatens":{}},{"id":13,"island":"florida","centroid":[29.298,-81.623],"mass":0.24,"count":14,"hull":[[29.238,-81.59],[29.245,-81.633],[29.335,-81.673],[29.371,-81.673],[29.371,-81.637],[29.299,-81.579]],"drift":{"speed":0.5,"bearing":239,"predictions":{"6h":{"centroid":[29.299,-81.661],"hull":[[29.239,-81.628],[29.282,-81.638],[29.319,-81.672],[29.34,-81.672],[29.372,-81.675],[29.3,-81.617]],"beached":false,"confidence":75},"12h":{"centroid":[29.304,-81.696],"hull":[[29.258,-81.653],[29.283,-81.649],[29.316,-81.675],[29.331,-81.675],[29.342,-81.672],[29.305,-81.652]],"beached":false,"confidence":55},"24h":{"centroid":[29.335,-81.751],"hull":[[29.291,-81.653],[29.293,-81.667],[29.321,-81.679],[29.333,-81.679],[29.344,-81.683],[29.327,-81.686]],"beached":false,"confidence":35},"48h":{"centroid":[29.373,-81.924],"hull":[[29.301,-81.671],[29.301,-81.665],[29.318,-81.685],[29.324,-81.685],[29.324,-81.679],[29.316,-81.684]],"beached":false,"confidence":22},"72h":{"centroid":[29.424,-82.078],"hull":[[29.307,-81.679],[29.308,-81.685],[29.314,-81.674],[29.318,-81.674],[29.325,-81.686],[29.315,-81.678]],"beached":false,"confidence":14}}},"threatens":{}},{"id":14,"island":"florida","centroid":[25.642,-80.237],"mass":0.23,"count":6,"hull":[[25.601,-80.259],[25.637,-80.259],[25.709,-80.223],[25.601,-80.223]],"drift":{"speed":0.5,"bearing":239,"predictions":{"6h":{"centroid":[25.643,-80.274],"hull":[[25.612,-80.281],[25.64,-80.262],[25.671,-80.247],[25.602,-80.26]],"beached":false,"confidence":75},"12h":{"centroid":[25.648,-80.308],"hull":[[25.627,-80.276],[25.642,-80.259],[25.659,-80.251],[25.616,-80.28]],"beached":false,"confidence":55},"24h":{"centroid":[25.679,-80.361],"hull":[[25.641,-80.256],[25.646,-80.256],[25.661,-80.257],[25.641,-80.257]],"beached":false,"confidence":35},"48h":{"centroid":[25.717,-80.529],"hull":[[25.645,-80.268],[25.649,-80.268],[25.656,-80.265],[25.645,-80.265]],"beached":false,"confidence":22},"72h":{"centroid":[25.768,-80.678],"hull":[[25.651,-80.283],[25.654,-80.283],[25.661,-80.28],[25.651,-80.28]],"beached":false,"confidence":14}}},"threatens":{"now":[{"id":"fl019","km":10},{"id":"fl002","km":19},{"id":"fl001","km":20}],"6h":[{"id":"fl019","km":13},{"id":"fl002","km":21},{"id":"fl001","km":22}],"12h":[{"id":"fl019","km":16},{"id":"fl002","km":23},{"id":"fl001","km":24}],"24h":[{"id":"fl019","km":21},{"id":"fl002","km":25},{"id":"fl001","km":26}]}},{"id":15,"island":"florida","centroid":[24.769,-81.275],"mass":0.2,"count":7,"hull":[[24.732,-81.275],[24.768,-81.347],[24.804,-81.239],[24.804,-81.203]],"drift":{"speed":0.5,"bearing":239,"predictions":{"6h":{"centroid":[24.77,-81.312],"hull":[[24.749,-81.296],[24.769,-81.357],[24.805,-81.276],[24.805,-81.24]],"beached":false,"confidence":75},"12h":{"centroid":[24.775,-81.345],"hull":[[24.738,-81.345],[24.772,-81.355],[24.81,-81.309],[24.81,-81.273]],"beached":false,"confidence":55},"24h":{"centroid":[24.806,-81.398],"hull":[[24.769,-81.367],[24.796,-81.421],[24.841,-81.362],[24.841,-81.326]],"beached":false,"confidence":35},"48h":{"centroid":[24.838,-81.542],"hull":[[24.801,-81.542],[24.837,-81.614],[24.873,-81.506],[24.873,-81.47]],"beached":true,"confidence":22},"72h":{"centroid":[24.847,-81.544],"hull":[[24.81,-81.544],[24.846,-81.616],[24.882,-81.508],[24.882,-81.472]],"beached":true,"confidence":14}}},"threatens":{"now":[{"id":"fl020","km":12},{"id":"fl009","km":20}],"6h":[{"id":"fl020","km":13},{"id":"fl009","km":24}],"12h":[{"id":"fl020","km":15},{"id":"fl009","km":27}],"24h":[{"id":"fl020","km":20}]}}]}